{"wArr":[11,11,11,11,11,12,11.75,11],"twArr":[97.75,85.75,73.75,61.75,49.75,37.75,24.75,12],"maxlv":1,"topicArr":[{"id":"n1pxsm9tr62662biwepj4qzzg4","state":"none","txt":"\u624b\u6bb5\uff1a\u5e7f\u544a\u6295\u653e\uff0c\u8d44\u6e90\u4e92\u6362\uff0c\u5fae\u4fe1\u7fa4\uff0c\u670b\u53cb\u5708","pid":"oqmu5d4ousxnq1obhgbfk2qlnu"},{"id":"oqmu5d4ousxnq1obhgbfk2qlnu","state":"close","txt":"\u5a92\u4f53\u5408\u4f5c","pid":"vq64t47hybruuw83kt7p8fwpvg"},{"id":"5oknwd3zr7xhba4nrfrugf9ylv","state":"none","txt":"\u6839\u636e\u7528\u6237\u8bbf\u95ee\u65f6\u95f4\u786e\u5b9a","pid":"qibghz152omgdfsv1fiuev86yq"},{"id":"qibghz152omgdfsv1fiuev86yq","state":"open","txt":"\u6295\u653e\u65f6\u95f4","pid":"4sgsro231yu25i6qszxof7vlla"},{"id":"nsqldvwrzvyuabq3eewlrbwit3","state":"none","txt":"\u9891\u6b21\uff1a\u6bcf\u59292\u7bc7\/\u4eba","pid":"baymwary9im5da6lub7ffk66bb"},{"id":"baymwary9im5da6lub7ffk66bb","state":"open","txt":"\u6295\u653e\u9891\u6b21","pid":"4sgsro231yu25i6qszxof7vlla"},{"id":"ksrr28sj2ty6ytu88gp5zr8fb6","state":"none","txt":"\u5982\u679c\u505a\u6700\u597d\u627e\u5b66\u751f\u517c\u804c","pid":"s8wnmibvbim49lnm79md3l2fgx"},{"id":"s8wnmibvbim49lnm79md3l2fgx","state":"open","txt":"\u8003\u8bd5\u8003\u70b9\uff0cQQ\uff0c\u53f8\u6cd5\uff0c\u4f1a\u8ba1\uff0c\u5927\u5b66\u79d1\u76ee","pid":"pb1uvooqw2rg6xf6fw8af1seg8"},{"id":"f4p7nl33oo9fdye955u35kq84x","state":"none","txt":"\u4e4b\u540e\u589e\u957f\u8f6c\u5176\u4ed6\u793e\u7fa4","pid":"pb1uvooqw2rg6xf6fw8af1seg8"},{"id":"pb1uvooqw2rg6xf6fw8af1seg8","state":"open","txt":"\u6bcf\u4e2a\u793e\u7fa4100~200\u6d3b\u8dc3\u7528\u6237\uff0c\u7ef4\u7cfb\u81ea\u7136\u589e\u957f","pid":"8re1ei15bbrjrufj686g6mvzb3"},{"id":"ptfvvrduueswwz54tyxtho1pzg","state":"none","txt":"\u7ebf\u4e0b\u6d3b\u52a8\uff0c\u5e72\u8d27\u6d3b\u52a8\u73b0\u573a\u7fa4\u5206\u4eab","pid":"8re1ei15bbrjrufj686g6mvzb3"},{"id":"jtis1ny82dauikm1btpf7own43","state":"none","txt":"\u521b\u4e1a\u8bba\u575b\uff0cqq\u7fa4","pid":"8re1ei15bbrjrufj686g6mvzb3"},{"id":"24p8423osb1kiujvmi5epr4kba","state":"none","txt":"\u8bbe\u8ba1\u5e08\u8bba\u575b\uff0cqq\u7fa4","pid":"8re1ei15bbrjrufj686g6mvzb3"},{"id":"6uodtqxb7vu19wm71vzwysz3zg","state":"none","txt":"\u8fd0\u8425\u793e\u533a\uff0cqq\u7fa4","pid":"8re1ei15bbrjrufj686g6mvzb3"},{"id":"afnruar1r7luuj46a2ktgxgyek","state":"none","txt":"\u5f00\u53d1\u8005\u8bba\u575b\uff0cqq\u7fa4","pid":"8re1ei15bbrjrufj686g6mvzb3"},{"id":"xlxd2oan8blezybt83kbuo7obx","state":"none","txt":"\u77e5\u4e4e\u793e\u533a","pid":"8re1ei15bbrjrufj686g6mvzb3"},{"id":"ofybj6odeua5v78bvdgqymugoz","state":"none","txt":"\u5929\u6daf\u793e\u533a","pid":"8re1ei15bbrjrufj686g6mvzb3"},{"id":"pvuioe2xsrbvdewodnyhrx4kdl","state":"none","txt":"\u8c46\u74e3\u5b98\u65b9","pid":"8re1ei15bbrjrufj686g6mvzb3"},{"id":"28mgwbfav4d818at5p3jzzzomg","state":"none","txt":"\u903b\u8f91\u601d\u7ef4\u793e\u533a\uff0cqq\u7fa4","pid":"8re1ei15bbrjrufj686g6mvzb3"},{"id":"ed9u2bg3r2vqdkkd66dk87urxu","state":"none","txt":"\u903b\u8f91\u601d\u7ef4\uff0c\u8bc4\u8bba\uff0c\u7fa4","pid":"8re1ei15bbrjrufj686g6mvzb3"},{"id":"95h2unjhs8maltgeqkkgwayptt","state":"none","txt":"\u4ea7\u54c1\u7ecf\u7406qq\u7fa4","pid":"8re1ei15bbrjrufj686g6mvzb3"},{"id":"bsqkliwkyoy988a7629atg8m2r","state":"none","txt":"\u65b0\u6d6a\u5fae\u535a\u4e3b\u9875","pid":"8re1ei15bbrjrufj686g6mvzb3"},{"id":"g8x8zubmdpmx8s41rw3bfibr94","state":"none","txt":"Facebook\u4e3b\u9875","pid":"8re1ei15bbrjrufj686g6mvzb3"},{"id":"fm6h9i24tynn9to6v4rh19h613","state":"none","txt":"QQ\u7fa4","pid":"8re1ei15bbrjrufj686g6mvzb3"},{"id":"k2vgtb2fm6ba4j25iv54nbhe28","state":"none","txt":"\u767e\u5ea6\u8111\u56fe\u8f6c\u5316","pid":"8re1ei15bbrjrufj686g6mvzb3"},{"id":"mzezbkzta48g4gmjo79gxwavha","state":"none","txt":"\u5fae\u4fe1\u7fa4","pid":"8re1ei15bbrjrufj686g6mvzb3"},{"id":"8re1ei15bbrjrufj686g6mvzb3","state":"close","txt":"\u6295\u653e\u6e20\u9053","pid":"4sgsro231yu25i6qszxof7vlla"},{"id":"uw2blj3f41ub7n3n8rbv4zhitg","state":"none","txt":"\u5f00\u53d1\uff0c\u4ea7\u54c1\uff0c\u8fd0\u8425\uff0c\u8bbe\u8ba1\uff0c\u8425\u9500\uff0c\u5fae\u4fe1\uff0c\u521b\u4e1a\u793e\u7fa4","pid":"gtyyqtsa5jk9bztfenrkukfbp4"},{"id":"lpeqmsds84j5dldetlewir8e6v","state":"none","txt":"\u52a0\u597d\u53cb\uff0c\u8981xmind\u548c\u767e\u5ea6\u8111\u56fe\u6e90\u6587\u4ef6\uff0c\u5bfc\u5165\u5230\u7af9\u8282\u8111\u56fe\uff0c\u540e\u5206\u4eab","pid":"gtyyqtsa5jk9bztfenrkukfbp4"},{"id":"brqnjgovohf1hymhbp2gbdbuth","state":"none","txt":"\u70ed\u70b9\u65b0\u95fb\uff0c\u516b\u5366\uff0c\u8f6c\u8111\u56fe","pid":"gtyyqtsa5jk9bztfenrkukfbp4"},{"id":"dfmsgxl9dh1gw6hamnf85uwkrz","state":"none","txt":"\u5c06\u4e13\u4e1a\u8bba\u575b\u70ed\u95e8\u5e16\u5b50\uff0c\u65b0\u95fb\uff0c\u5df2\u8111\u56fe\u5f62\u5f0f\u8ddf\u5e16\uff0c\u8bc4\u8bba\uff0c\u6216\u65b0\u5efa\u6761\u76ee","pid":"gtyyqtsa5jk9bztfenrkukfbp4"},{"id":"a3nrebtif8gi2spyoqwypkrtvs","state":"none","txt":"\u4ea7\u54c1\uff0c\u8bbe\u8ba1\uff0c\u8fd0\u8425\u5e72\u8d27\uff0c\u8f6c\u8111\u56fe","pid":"gtyyqtsa5jk9bztfenrkukfbp4"},{"id":"gtyyqtsa5jk9bztfenrkukfbp4","state":"open","txt":"\u6295\u653e\u5185\u5bb9","pid":"4sgsro231yu25i6qszxof7vlla"},{"id":"1m3zbda8w4bg47qbbbruq7kips","state":"none","txt":"\u76ee\u6807\u4eba\u7fa4","pid":"4sgsro231yu25i6qszxof7vlla"},{"id":"4sgsro231yu25i6qszxof7vlla","state":"open","txt":"\u63a8\u5e7f\u6e20\u9053","pid":"vq64t47hybruuw83kt7p8fwpvg"},{"id":"vq64t47hybruuw83kt7p8fwpvg","state":"open","txt":"\u5de5\u4f5c\u62c6\u5206","pid":"dpnskklzj3bbt2n1ywvkerdh8h"},{"id":"bsvj7ibw4bwiypzion51oxb548","state":"none","txt":"\u540c\u7c7b\u5de5\u5177\u5c24\u5176\u662f\u8111\u56fe\u5de5\u5177saas\u5e73\u53f0\u7684\u8bbf\u95ee","pid":"rbhemfogbxxrabw1f16khb34at"},{"id":"rbhemfogbxxrabw1f16khb34at","state":"open","txt":"\u5e02\u573a\u8c03\u67e5","pid":"ve4iizaziu2hqbdbg4w3v2k3pf"},{"id":"178ibih1g7a9vfkkaqx372kqbb","state":"none","txt":"appsore\u8bc4\u5206","pid":"zztjqj61xeaq6aev4tns542hte"},{"id":"h9lev21fi6trvtpt2yxvobuyj7","state":"none","txt":"\u95ee\u5377","pid":"zztjqj61xeaq6aev4tns542hte"},{"id":"g37hzlvqmvb5aidmi35wdfdh2a","state":"none","txt":"\u76ee\u6807\uff0c\u7528\u6237\u6ee1\u610f\u7a0b\u5ea6\uff0c\u4f18\u5148\u79cd\u5b50\u7528\u6237","pid":"zztjqj61xeaq6aev4tns542hte"},{"id":"zztjqj61xeaq6aev4tns542hte","state":"open","txt":"\u7528\u6237\u8c03\u7814","pid":"ve4iizaziu2hqbdbg4w3v2k3pf"},{"id":"4hlbquwa3w6685npa8edub8bqi","state":"none","txt":"\u6d3b\u8dc3\u7528\u6237\u6570\uff0c\u770b\u7684\u662f\u4ea7\u54c1\u7684\u5e02\u573a\u4f53\u91cf\u3002\u6d3b\u8dc3\u7387\uff0c\u770b\u7684\u662f\u4ea7\u54c1\u7684\u5065\u5eb7\u5ea6\u3002 ","pid":"mojsuzip59bdv83wk6widvv6ih","image":"http:\/\/mapidev.weavent.com\/image\/view\/4ee6c962b8c0fea47679a2141212e479_308.png"},{"id":"mojsuzip59bdv83wk6widvv6ih","state":"open","txt":"\u6d3b\u8dc3\u7387","pid":"72b448ef1li1i92texsu94wm9t"},{"id":"lgz6l1d5twmbp1juatph58lgnz","state":"none","txt":"\u4f8b\u5b50","pid":"g2awyomny8tdrtd57m4rqqyhn9","image":"http:\/\/mapidev.weavent.com\/image\/view\/fac4ac009c7321bdd075e54819251dd7_224.png"},{"id":"9iof19pumygo94l7tj848tfym3","state":"none","txt":"\u65e5\u5747\u4f7f\u7528\u65f6\u957f","pid":"g2awyomny8tdrtd57m4rqqyhn9"},{"id":"sfe2sb6zwsiggtie9uh65ykbtw","state":"none","txt":"\u65e5\u5747\u8bbf\u95ee\u6b21\u6570","pid":"g2awyomny8tdrtd57m4rqqyhn9"},{"id":"g2awyomny8tdrtd57m4rqqyhn9","state":"open","txt":"\u6307\u6807","pid":"72b448ef1li1i92texsu94wm9t"},{"id":"je5ndtdeafioaqbyqib9j5z6vd","state":"none","txt":"\u80fd\u4f5c\u4e3a\u751f\u4ea7\u529b\u5de5\u5177\u4f7f\u7528\u7684\u5e94\u7528\uff0c\u6beb\u65e0\u7591\u95ee\uff0c\u6709\u53ef\u80fd\u53ef\u4ee5\u4ea7\u751f\u6700\u5927\u6700\u9ad8\u7684\u7528\u6237\u65e5\u6d3b\u8dc3\u5ea6","pid":"gr6qhjvmvlk5zffmzk6dej5hbb"},{"id":"gr6qhjvmvlk5zffmzk6dej5hbb","state":"open","txt":"\u6d3b\u8dc3\u5ea6\u4e00\u822c\u662f\u6307\u7ebf\u4e0a\u4ea7\u54c1\u7684\u7528\u6237\u5728\u7ebf\u65f6\u957f\u4ee5\u53ca\u767b\u5f55\u9891\u6b21\u3002","pid":"72b448ef1li1i92texsu94wm9t"},{"id":"72b448ef1li1i92texsu94wm9t","state":"open","txt":"\u6d3b\u8dc3\u5ea6","pid":"az7pfa5wsyn172l9s2arkdbzyn"},{"id":"ji2ltp9p4bvl2gqruy5x1v6ki7","state":"none","txt":"\u76c8\u4e8f\u5e73\u8861","pid":"bvpoxwxju3ygf4142fhw9mwvw1"},{"id":"bvpoxwxju3ygf4142fhw9mwvw1","state":"open","txt":"\u8f6c\u531610%\uff0c\u8425\u6536200\u4e07","pid":"kjr9mo6lkajk5jbro8npjl7noq"},{"id":"kjr9mo6lkajk5jbro8npjl7noq","state":"open","txt":"\u65e5\u589e60\uff0c\u5e74\u589e2\u4e07","pid":"lv7si29n6seek54i3u3jquis5x"},{"id":"lv7si29n6seek54i3u3jquis5x","state":"open","txt":"\u76ee\u6807\u65b0\u589e2000\/\u6708","pid":"bzlksgml3u6xs2r2kyaulrg24l"},{"id":"bzlksgml3u6xs2r2kyaulrg24l","state":"open","txt":"\u7528\u6237\u6570","pid":"az7pfa5wsyn172l9s2arkdbzyn"},{"id":"y9vsaxhqbh7n8roiq7rv5xqjj1","state":"none","txt":"\u6bcf\u4eba\u8d1f\u8d23\u65e5\u589e6\u6d3b\u8dc3","pid":"lb81wrltzzpydwf1ilwlwzj9fg"},{"id":"lb81wrltzzpydwf1ilwlwzj9fg","state":"open","txt":"\u65e5\u589e\u6d3b\u8dc3\u7528\u6237\u657030\uff0c1\u4e2a\u6708\u540e1k","pid":"ahzw8ny113grzjjelrbm5u9r39"},{"id":"ahzw8ny113grzjjelrbm5u9r39","state":"open","txt":"PV=100,000\uff0c\u6d3b\u8dc3\u7528\u62371000","pid":"rfvrv5gga4ivy8o1g8riurt6gw"},{"id":"hzbw3pda3bxw7idamidx7h7efi","state":"none","txt":"\u76ee\u524dPV=300 \uff0c\u6d3b\u8dc3\u7528\u62373","pid":"rfvrv5gga4ivy8o1g8riurt6gw"},{"id":"rfvrv5gga4ivy8o1g8riurt6gw","state":"open","txt":"\u76ee\u6807\uff08PV\uff09","pid":"m512bamhxiqasilsu2ugoov3qa"},{"id":"5fqkizfokibmvwrvxrxndy9r2z","state":"none","txt":"\u5076\u7136\u56e0\u7d20","pid":"ebgpgk2aznfmsxswfby3rbdu8d"},{"id":"jhee27ubsb8zauldhfvbszmawo","state":"none","txt":"\u7a81\u53d1\u4e8b\u4ef6","pid":"ebgpgk2aznfmsxswfby3rbdu8d"},{"id":"6rhl6f7zlhkzbbasfr5pi23klo","state":"none","txt":"\u8bbf\u95ee\u5468\u671f","pid":"ebgpgk2aznfmsxswfby3rbdu8d"},{"id":"p53ztmavse1y2t2xz7sqojs111","state":"none","txt":"\u7f16\u8f91\u624b\u6bb5","pid":"ebgpgk2aznfmsxswfby3rbdu8d"},{"id":"ebgpgk2aznfmsxswfby3rbdu8d","state":"open","txt":"\u5f71\u54cd\u56e0\u7d20","pid":"m512bamhxiqasilsu2ugoov3qa"},{"id":"axb19gqwwbb7rhqfynxbbq8g2b","state":"none","txt":"PV=100,000 ","pid":"975km5iuk8zt25b6si7zrqt4nx"},{"id":"975km5iuk8zt25b6si7zrqt4nx","state":"open","txt":"36Kr\u521d\u671f","pid":"pjf624yb7bpail1tuzsgsrs6d7"},{"id":"9uroa1do9ptw4bn7x51azdrsz9","state":"none","txt":"PV=828,000","pid":"ud5bjt9458xe9kbs5nbqd6y12x"},{"id":"ng5866mfhbl19qsj1g3qoz3m9d","state":"none","txt":"UV=138,000","pid":"ud5bjt9458xe9kbs5nbqd6y12x"},{"id":"ud5bjt9458xe9kbs5nbqd6y12x","state":"open","txt":"\u679c\u58f3\u7f51","pid":"pjf624yb7bpail1tuzsgsrs6d7"},{"id":"yuk9eqx7e2glxgswo87uvlooew","state":"none","txt":"PV=9,240,000\n","pid":"6jqbxw22m5k1reoy5jh6k67x5p"},{"id":"z2gf91s578hxefx6a2jaypeovr","state":"none","txt":"UV=528,000","pid":"6jqbxw22m5k1reoy5jh6k67x5p"},{"id":"6jqbxw22m5k1reoy5jh6k67x5p","state":"open","txt":"\u6c7d\u8f66\u4e4b\u5bb6","pid":"pjf624yb7bpail1tuzsgsrs6d7"},{"id":"ba66uqk8vfaxqnviyyle5vqvay","state":"none","txt":"PV=703,278,000","pid":"wfyosma7yxa724y2lewxgipbnd"},{"id":"pdsz3s6xb3j3h2wq7wshbs8kls","state":"none","txt":"UV=80,100\uff0c000,","pid":"wfyosma7yxa724y2lewxgipbnd"},{"id":"wfyosma7yxa724y2lewxgipbnd","state":"open","txt":"\u767e\u5ea6\u3001\u6dd8\u5b9d\u3001\u65b0\u6d6a\u5fae\u535a\n","pid":"pjf624yb7bpail1tuzsgsrs6d7"},{"id":"8qey5bpsipn3jfumy34k9q6wl8","state":"none","txt":"PV=7,107,998,400","pid":"y8669tln4yhfbukta6xfs41gnm"},{"id":"uoku3fuml3zg3qhb7apm11jxbz","state":"none","txt":"UV=295,920,000","pid":"y8669tln4yhfbukta6xfs41gnm"},{"id":"y8669tln4yhfbukta6xfs41gnm","state":"open","txt":"Google\n","pid":"pjf624yb7bpail1tuzsgsrs6d7"},{"id":"m2ur8vbqzsxs4hga27fy7o6x9f","state":"none","txt":"UV\u662f\u4e00\u4e2a\u53cd\u6620\u5b9e\u9645\u4f7f\u7528\u8005\u7684\u6982\u5ff5\uff0c\u6bcf\u4e2aUV\u76f8\u5bf9\u4e8e\u6bcf\u4e2aIP\uff0c\u66f4\u52a0\u51c6\u786e\u5730\u5bf9\u5e94\u4e00\u4e2a\u5b9e\u9645\u7684\u6d4f\u89c8\u8005\u3002\u4f7f\u7528UV\u4f5c\u4e3a\u7edf\u8ba1\u91cf\uff0c\u53ef\u4ee5\u66f4\u52a0\u51c6\u786e\u7684\u4e86\u89e3\u5355\u4f4d\u65f6\u95f4\u5185\u5b9e\u9645\u4e0a\u6709\u591a\u5c11\u4e2a\u8bbf\u95ee\u8005\u6765\u5230\u4e86\u76f8\u5e94\u7684\u9875\u9762\u3002","pid":"5o495qvm8o54swru4p7t46jq83"},{"id":"5o495qvm8o54swru4p7t46jq83","state":"open","txt":"PV\uff08page view\uff09\u5373\u9875\u9762\u6d4f\u89c8\u91cf\uff0c\u901a\u5e38\u662f\u8861\u91cf\u4e00\u4e2a\u7f51\u7edc\u65b0\u95fb\u9891\u9053\u6216\u7f51\u7ad9\u751a\u81f3\u4e00\u6761\u7f51\u7edc\u65b0\u95fb\u7684\u4e3b\u8981\u6307\u6807\u3002","pid":"pjf624yb7bpail1tuzsgsrs6d7"},{"id":"pjf624yb7bpail1tuzsgsrs6d7","state":"open","txt":"\u6307\u6807","pid":"m512bamhxiqasilsu2ugoov3qa"},{"id":"m512bamhxiqasilsu2ugoov3qa","state":"open","txt":"PV\uff08page View\uff09\/UV","pid":"az7pfa5wsyn172l9s2arkdbzyn"},{"id":"9h59qw4njevve6a2mhrgpf8igx","state":"none","txt":"\u7edf\u8ba1\u6e20\u9053\uff0cappstore","pid":"bl6bb2i3ba1aorlt84sd3v7jjn"},{"id":"bl6bb2i3ba1aorlt84sd3v7jjn","state":"open","txt":"\u4e0b\u8f7d","pid":"8xpkznadu65zztsy4uq38qaqy1"},{"id":"m7ual8rpm8gfyxzbowkgbpr8h6","state":"none","txt":"\u76ee\u680710%\uff0c1\u5e74\u5b9e\u73b0\u76c8\u4e8f\u5e73\u8861","pid":"u6ykkbk2hyhz5sdmzla9aub1nw"},{"id":"u6ykkbk2hyhz5sdmzla9aub1nw","state":"open","txt":"\u7528\u6237\u6570\uff0c\u4ed8\u8d39\u8f6c\u5316","pid":"8xpkznadu65zztsy4uq38qaqy1"},{"id":"e9ll73bm7llvwd6hpdmrgglrkw","state":"none","txt":"\u4fdd\u8bc1PV\uff0cUV\u91cf","pid":"1bnw17peo991jge6b137t2o9su"},{"id":"1bnw17peo991jge6b137t2o9su","state":"open","txt":"\u6d3b\u8dc3\u7528\u6237\u6570","pid":"8xpkznadu65zztsy4uq38qaqy1"},{"id":"wht8tim418zm93d3i6n59shxur","state":"none","txt":"\u4ea7\u54c1\u7684\u8bbf\u95ee\u7a0b\u5ea6","pid":"fwfbvkdb9dydrm3g1wyu741xeb"},{"id":"fwfbvkdb9dydrm3g1wyu741xeb","state":"open","txt":"PV\/UV","pid":"8xpkznadu65zztsy4uq38qaqy1"},{"id":"8xpkznadu65zztsy4uq38qaqy1","state":"close","txt":"\u5d4c\u5165\u94fe\u63a5\u5206\u6790","pid":"az7pfa5wsyn172l9s2arkdbzyn"},{"id":"az7pfa5wsyn172l9s2arkdbzyn","state":"open","txt":"\u6570\u636e\u5206\u6790","pid":"ve4iizaziu2hqbdbg4w3v2k3pf"},{"id":"ve4iizaziu2hqbdbg4w3v2k3pf","state":"open","txt":"\u4efb\u52a1\u76ee\u6807","pid":"dpnskklzj3bbt2n1ywvkerdh8h"},{"id":"k6jshkd5qfrp2m5pb72b5bnxnv","state":"none","txt":"\u534f\u8bae\u9875","pid":"zs3ym1wi9r5bunx374d5n5tejg"},{"id":"9rgxyfajobk2d4mbl27rbwmrsz","state":"none","txt":"\u9996\u6279\u79cd\u5b50\u7528\u6237\uff0c\u7edf\u8ba1\uff0c\u6dfb\u52a0vip\u6743\u9650","pid":"zs3ym1wi9r5bunx374d5n5tejg"},{"id":"pp17z675djszt7u16aglx9ble8","state":"none","txt":"\u64cd\u4f5c\u8bf4\u660e","pid":"zs3ym1wi9r5bunx374d5n5tejg"},{"id":"9j6e6mdbizw5lnyy7log4blw9k","state":"none","txt":"\u529f\u80fd\u4ecb\u7ecd\u89c6\u9891","pid":"zs3ym1wi9r5bunx374d5n5tejg"},{"id":"9ooqsk5wshykr57n8yzs4h8wfx","state":"none","txt":"\u4ea7\u54c1\u7b80\u4ecb\u6587\u5b57\uff0cH5","pid":"zs3ym1wi9r5bunx374d5n5tejg"},{"id":"zs3ym1wi9r5bunx374d5n5tejg","state":"open","txt":"\u4ea7\u54c1\u5de5\u4f5c","pid":"g9mfzxlo5vqyn34z2betvloxnb"},{"id":"uwum2ip7vy2uo9fggil1deiqla","state":"none","txt":"\u63d0\u5347\u6548\u7387\uff0c\u5b9e\u65f6\u53d1\u8868\uff0c\u6d3b\u52a8\u73b0\u573a\u7684\u610f\u89c1\u9886\u8896","pid":"vh6j842z1nbmsrgns4exjjdmju","image":"http:\/\/mapidev.weavent.com\/image\/view\/c605a7b0486453aa989b6fb03a3c99b7_352.jpg"},{"id":"vh6j842z1nbmsrgns4exjjdmju","state":"open","txt":"\u73b0\u573a\u7b14\u8bb0\u8bb0\u5f55","pid":"abpu9hxzxp4d3burmk24lqknap"},{"id":"wzm6ojegnn9i7qpu1k2681rs5x","state":"none","txt":"","pid":"7bbl41advjn1e8nkw8gnk3ru7m","image":"http:\/\/mapidev.weavent.com\/image\/view\/2fd2abd55f854ae69d597efd37d54245_352.jpg"},{"id":"7bbl41advjn1e8nkw8gnk3ru7m","state":"open","txt":"\u903b\u8f91\u601d\u7ef4\u4e00\u671f\u8282\u76ee40\u5206\u949f\uff0c\u8111\u56fe\u9605\u8bfb5\u5206\u949f","pid":"abpu9hxzxp4d3burmk24lqknap"},{"id":"vqlwv8vmo4t9ylm7b7dab6x6r8","state":"none","txt":"\u9605\u8bfb\u65f6\u95f4\u51cf\u5c1187%","pid":"abpu9hxzxp4d3burmk24lqknap"},{"id":"abpu9hxzxp4d3burmk24lqknap","state":"open","txt":"\u6548\u679c","pid":"g9mfzxlo5vqyn34z2betvloxnb"},{"id":"bpzue8mea5pfd7xfyk38zsb1uq","state":"none","txt":"\u4f53\u9a8c\u6700\u4f73\uff0c\u6ca1\u6709\u4e4b\u4e00","pid":"vhyixilmq1vh26sdl4nywt24td"},{"id":"vhyixilmq1vh26sdl4nywt24td","state":"open","txt":"\u79fb\u52a8\u7aef\u7f16\u8f91","pid":"b22t9h7btlxe4pdzgede2fkgdy"},{"id":"ea4le8ay8tzhhwk7dhykwn7186","state":"none","txt":"\u79fb\u52a8\u7aef\uff0cpc\uff0c\u7edf\u4e00\u9875\u9762\uff0c\u7edf\u4e00\u4f53\u9a8c","pid":"7y4l5g1p81hpj9waetv7ui3uzr"},{"id":"7y4l5g1p81hpj9waetv7ui3uzr","state":"open","txt":"\u6240\u6709\u5e73\u53f0\u9002\u914d","pid":"b22t9h7btlxe4pdzgede2fkgdy"},{"id":"f2jkse6vqam4pzbto5mkwyjzrp","state":"none","txt":"\u81ea\u5df1\u5f00\u53d1\u7684\u8de8\u5e73\u53f0\u67b6\u6784\uff0c\u6027\u80fd\u8d85\u8d8a\u73b0\u5b58\u6240\u6709web\u8111\u56fe\u52a0\u8f7d\u65b9\u5f0f","pid":"wixaaukxgjfnv1w76eqozxkzw3"},{"id":"wixaaukxgjfnv1w76eqozxkzw3","state":"open","txt":"\u52a0\u8f7d\u65f6\u95f4300ms","pid":"b22t9h7btlxe4pdzgede2fkgdy"},{"id":"goo6ornd99xsn34wjfl8namsbt","state":"none","txt":"\u8d85\u8d8a\u539f\u751f\u7684\u9605\u8bfb\u4f53\u9a8c\uff0c\u65e0\u767d\u5c4f\uff0c\u4e13\u5229\u7533\u8bf7","pid":"u6td2s73k85d5gk5wf4u1qq46d","image":"http:\/\/mapidev.weavent.com\/image\/view\/8cac54d547adb309c45c9dfeacef464b_352.gif"},{"id":"u6td2s73k85d5gk5wf4u1qq46d","state":"open","txt":"\u878d\u5408\u5f0f\u9875\u9762\uff0c\u65e0\u5ef6\u65f6\u52a0\u8f7d","pid":"b22t9h7btlxe4pdzgede2fkgdy"},{"id":"w14yvtxbmr97e9oweru2dk39ab","state":"none","txt":"\u7ed3\u5408\u6240\u6709\u67e5\u770b\u65b9\u5f0f\u7684\u6709\u70b9\uff0c\u5b50\u4e3b\u9898\u70b9\u51fb\u4e0b\u94bb","pid":"fb8ds4vr84jmbae5oiofjxdyax"},{"id":"fb8ds4vr84jmbae5oiofjxdyax","state":"open","txt":"\u591a\u6837\uff0c\u53ef\u89c6\u5316\u7684\u4fe1\u606f\u7ed3\u6784","pid":"b22t9h7btlxe4pdzgede2fkgdy"},{"id":"b22t9h7btlxe4pdzgede2fkgdy","state":"open","txt":"\u89e3\u51b3","pid":"g9mfzxlo5vqyn34z2betvloxnb"},{"id":"6inbbptk9fj6gbglbl8l7bn5vf","state":"none","txt":"con\uff1a\u5927\u4e8e2\u7ea7\u65e0\u6cd5\u663e\u793a","pid":"fb6je81vpsfyawkkwmqxzqglof"},{"id":"wwues4vxr94l7bt3qbzfz3dyyr","state":"none","txt":"pro\uff1a2\u7ea7\u4ee5\u5185\uff0c\u6700\u9002\u5408","pid":"fb6je81vpsfyawkkwmqxzqglof"},{"id":"fb6je81vpsfyawkkwmqxzqglof","state":"open","txt":"trello","pid":"iypktoise5mo96hm9ft5gaqt3q"},{"id":"iypktoise5mo96hm9ft5gaqt3q","state":"open","txt":"\u770b\u677f\u89c6\u56fe","pid":"b4uiukbwu3z4z553w2vpwddgq6"},{"id":"f8nolo9udab3ddhpoo1pu6ujyj","state":"none","txt":"con\uff1a\u624b\u673a\u7aef\u67e5\u770b\uff0c\u4fe1\u606f\u591a\u65f6\u4e0d\u9002\u5408\u9605\u8bfb","pid":"ftebe6aekkgd7bx6ob7gj6oyjx"},{"id":"jzpkbj8n2invpljs3mimwp1xku","state":"none","txt":"pro\uff1a\u5927\u4fe1\u606f\uff0c\u56fe\u6587","pid":"ftebe6aekkgd7bx6ob7gj6oyjx"},{"id":"ftebe6aekkgd7bx6ob7gj6oyjx","state":"open","txt":"Xmind","pid":"x6anhw3lywvg587wn3jejv3qf8"},{"id":"x6anhw3lywvg587wn3jejv3qf8","state":"open","txt":"\u8111\u56fe\u89c6\u56fe","pid":"b4uiukbwu3z4z553w2vpwddgq6"},{"id":"d61b11wq7h4jjpwzfrb7js7wwa","state":"none","txt":"con\uff1a\u4fe1\u606f\u5927\uff0c\u89c2\u70b9\u590d\u6742","pid":"ultusblqly9ja47hygeahgqlrh"},{"id":"bpnmfwnbgyj7o59o8msvzmavun","state":"none","txt":"pro\uff1a\u5c11\u4fe1\u606f\uff0c\u56fe\u6587","pid":"ultusblqly9ja47hygeahgqlrh"},{"id":"ultusblqly9ja47hygeahgqlrh","state":"open","txt":"ppt","pid":"v2vydea2br3tn8tr9ikvhfype6"},{"id":"v2vydea2br3tn8tr9ikvhfype6","state":"open","txt":"\u6f14\u793a\u89c6\u56fe","pid":"b4uiukbwu3z4z553w2vpwddgq6"},{"id":"3ul7s3ksbb2hxpdbtb4manqlj6","state":"none","txt":"con\uff1a\u5185\u5bb9\u591a\u65f6\u96be\u4ee5\u9605\u8bfb","pid":"vfuu4jw8q3wtsnw3ujjs86koft"},{"id":"wjn29mbfm5ypi1aoqo4ok2rrm1","state":"none","txt":"pro\uff1a\u5c42\u7ea7\u76f4\u89c2","pid":"vfuu4jw8q3wtsnw3ujjs86koft"},{"id":"vfuu4jw8q3wtsnw3ujjs86koft","state":"open","txt":"excel","pid":"ns3b61guz8oup1yl4i6bqpnqh6"},{"id":"ns3b61guz8oup1yl4i6bqpnqh6","state":"open","txt":"\u7f51\u683c\u89c6\u56fe","pid":"b4uiukbwu3z4z553w2vpwddgq6"},{"id":"rjmqdz1t6fnyfusrbdjyvljpez","state":"none","txt":"con\uff1a\u4e0d\u76f4\u89c2","pid":"vb42auiikgsvs2akb6lzf35yza"},{"id":"de4h1nugyq2ulwse3qfn48xxbb","state":"none","txt":"pro\uff1a20\u884c\u4ee5\u5185\u7684\u591a\u7ea7\uff0c\u9002\u5408\u9605\u8bfb\u4e60\u60ef\uff08\u76f4\u7ebf\uff09","pid":"vb42auiikgsvs2akb6lzf35yza"},{"id":"vb42auiikgsvs2akb6lzf35yza","state":"open","txt":"word","pid":"bbspdaimibndq88fwmmzzxu5sr"},{"id":"bbspdaimibndq88fwmmzzxu5sr","state":"open","txt":"\u5927\u7eb2\u89c6\u56fe","pid":"b4uiukbwu3z4z553w2vpwddgq6"},{"id":"b4uiukbwu3z4z553w2vpwddgq6","state":"open","txt":"\u6bd4\u8f83","pid":"g9mfzxlo5vqyn34z2betvloxnb"},{"id":"j3heeb5285t7oxwth622reb2s2","state":"none","txt":"\u4f8b\uff1azaker\uff0c\u623f\u4ef7\u662f\u5426\u4f1a\u957f","pid":"eyeq126v5i8ivgkkdq4nvaslgb"},{"id":"pn7edb3dbs3yjxms726u8kplpd","state":"none","txt":"\u9605\u8bfb\u65b0\u95fb\uff0c\u6570\u636e\u548c\u4f8b\u5b50\u4e4b\u95f4\u662f\u5426\u5b58\u5728\u771f\u5b9e\u652f\u6491","pid":"eyeq126v5i8ivgkkdq4nvaslgb"},{"id":"eyeq126v5i8ivgkkdq4nvaslgb","state":"open","txt":"\u5927\u91cf\u4fe1\u606f\u771f\u4f2a","pid":"8f3m5468dbmhzk82x1j2jpakgk"},{"id":"mrbyg9et5esoufbt2v54mqnee7","state":"none","txt":"\u4f8b\uff1amaterialdesign\uff0c\u8bbe\u8ba1\u53c2\u6570\uff0c\u8272\u677f","pid":"r1essbeabrpgln1sry71avjx38"},{"id":"mz4gr8jbdun9b29py5od5m7f8s","state":"none","txt":"\u8bbe\u8ba1app\u754c\u9762\uff0c\u77ed\u65f6\u95f4\u5904\u7406\uff0c\u67e5\u627e\u5927\u91cf\u4fe1\u606f","pid":"r1essbeabrpgln1sry71avjx38"},{"id":"r1essbeabrpgln1sry71avjx38","state":"open","txt":"\u5927\u91cf\u4fe1\u606f\u68c0\u7d22","pid":"8f3m5468dbmhzk82x1j2jpakgk"},{"id":"ya416uwhxsala32lwrvd3b1b8n","state":"none","txt":"\u4f8b\uff1a\u5fc3\u91cc\u5b66\uff0c\u8003\u8bd5","pid":"fjvpevjikpt6teeegjbshhzbeq"},{"id":"an6ze7iuysbp5nz4brii5i4jiq","state":"none","txt":"\u8003\u8bd5\u4e4b\u524d\uff0c\u4fe1\u606f\u7206\u70b8\uff0c\u5982\u4f55\u4e00\u76ee\u5341\u884c","pid":"fjvpevjikpt6teeegjbshhzbeq"},{"id":"fjvpevjikpt6teeegjbshhzbeq","state":"open","txt":"\u5927\u91cf\u4fe1\u606f\u67e5\u770b","pid":"8f3m5468dbmhzk82x1j2jpakgk"},{"id":"unb9ubhbeadf4fvkegsu5sbnra","state":"none","txt":"\u4f8b\uff1a\u77e5\u4e4e\uff0c\u5f15\u529b\u6ce2","pid":"rakhvv73splbknxv7jrlkk94si"},{"id":"xv78a1m9f213p4guin9xx7yu4p","state":"none","txt":"\u77e5\u4e4e\u4e13\u5bb6\uff0c\u4f20\u9012\u5927\u91cf\u4fe1\u606f\uff0c\u6210\u4e3a\u6df1\u5ea6\u7684\u610f\u89c1\u9886\u8896","pid":"rakhvv73splbknxv7jrlkk94si"},{"id":"rakhvv73splbknxv7jrlkk94si","state":"open","txt":"\u5927\u91cf\u4fe1\u606f\u4f20\u64ad","pid":"8f3m5468dbmhzk82x1j2jpakgk"},{"id":"a391t2a9zgfs15v7kxxnq5zg2j","state":"none","txt":"\u5feb\u901f\u8bb0\u5f55\uff0c\u9605\u8bfb","pid":"hdzypnv7p6lamvo4557vp23faq"},{"id":"hdzypnv7p6lamvo4557vp23faq","state":"open","txt":"\u603b\u7ed3\uff1a\u5927\u91cf\u4fe1\u606f\u7684\u6c9f\u901a","pid":"8f3m5468dbmhzk82x1j2jpakgk"},{"id":"8f3m5468dbmhzk82x1j2jpakgk","state":"open","txt":"\u75db\u70b9","pid":"g9mfzxlo5vqyn34z2betvloxnb"},{"id":"g9mfzxlo5vqyn34z2betvloxnb","state":"close","txt":"\u4ea7\u54c1\u63cf\u8ff0","pid":"dpnskklzj3bbt2n1ywvkerdh8h"},{"id":"dpnskklzj3bbt2n1ywvkerdh8h","state":"open","txt":"\u8111\u56fe\u8fd0\u8425","pid":"canvas"}]}