{"wArr":[8,12.625,20.6875,15.6875],"twArr":[61,52,38.375,16.6875],"maxlv":4,"topicArr":[{"id":"er1k3bw5be87n1xl62h2rz3xa4","state":"open","txt":"\u529e\u516c\u5ba4\u5de5\u4f5c","pid":"canvas"},{"id":"pko1ou2b591dz721mftto2bm3v","state":"open","txt":"\u5370\u7ae0\u7ba1\u7406","pid":"er1k3bw5be87n1xl62h2rz3xa4"},{"id":"axaoafvb47kvif2uu7kt3xglab","state":"none","txt":"\u674e\u627f\u94a2\u8d1f\u8d23\u7ba1\u7406","pid":"pko1ou2b591dz721mftto2bm3v"},{"id":"q2m7ib1ax5a35xgrxkdpho8lut","state":"none","txt":"\u5404\u804c\u5de5\u4f7f\u7528\u65f6\u767b\u8bb0","pid":"pko1ou2b591dz721mftto2bm3v"},{"id":"bbs73es37bb2v1ozro5zzgwdsq","state":"open","txt":"\u529e\u516c\u91c7\u8d2d\u53d1\u653e\u7ba1\u7406","pid":"er1k3bw5be87n1xl62h2rz3xa4"},{"id":"qkbxemreivzrrnsj9ek45lba6q","state":"none","txt":"\u674e\u627f\u94a2\u548c\u5434\u5229\u5a1c\u5171\u540c\u5b8c\u6210","pid":"bbs73es37bb2v1ozro5zzgwdsq"},{"id":"uu1pwayzh8g7gkxbrvjbnhssjl","state":"open","txt":"\u5404\u7c7b\u8d28\u91cf\u6587\u4e66\u7f16\u53f7\u3001\u767b\u8bb0\u548c\u5b58\u6863\uff08\u544a\u77e5\u4e66\u3001\u6574\u6539\u548c\u505c\u5de5\u901a\u77e5\u4e66\u7b49\uff09","pid":"er1k3bw5be87n1xl62h2rz3xa4"},{"id":"ytrb9f2rdf6ht1u6t6r3g878dm","state":"none","txt":"\u674e\u627f\u94a2\u8d1f\u8d23\u6536\u96c6\u5b58\u6863","pid":"uu1pwayzh8g7gkxbrvjbnhssjl"},{"id":"6d1bnybeeq8ag89oxi4ph5shsb","state":"open","txt":"\u7eb8\u8d28\u4ef6\u6765\u6587\u7ba1\u7406","pid":"er1k3bw5be87n1xl62h2rz3xa4"},{"id":"lf49gadxl44xufdiwrp9bsiaa5","state":"open","txt":"\u6536\u6587\u767b\u8bb0\u3001\u5448\u9886\u5bfc\u9605\u5904\u548c\u5f52\u7c7b\u5b58\u6863","pid":"6d1bnybeeq8ag89oxi4ph5shsb"},{"id":"9v7m6ifv48nifaurwtvyrapkyw","state":"none","txt":"\u674e\u627f\u94a2\u548c\u5434\u5229\u5a1c\u5171\u540c\u5b8c\u6210","pid":"lf49gadxl44xufdiwrp9bsiaa5"},{"id":"p23x5l9vo65lbfpie4x5xj1syy","state":"open","txt":"\u5176\u4ed6\u6765\u6e90\u4fe1\u606f\u6536\u96c6\u5904\u7406","pid":"er1k3bw5be87n1xl62h2rz3xa4"},{"id":"fl757lpt8msqjym7lkmtwg56bx","state":"open","txt":"\u5e02\u7ad9\u529e\u516cQQ\u7fa4\u3001\u5b89\u88c5\u5fae\u4fe1\u7fa4","pid":"p23x5l9vo65lbfpie4x5xj1syy"},{"id":"l45wnp8d19gesbk658o1qpail2","state":"none","txt":"\u5e9e\u4ed9\u7eea\u6536\u96c6\u540e\u4ea4\u674e\u627f\u94a2\u6536\u6587","pid":"fl757lpt8msqjym7lkmtwg56bx"},{"id":"ljvt71upg2btpuypxhp8rhvth7","state":"open","txt":"\u5e02\u7ad9\u603b\u5de5\u529eQQ\u7fa4","pid":"p23x5l9vo65lbfpie4x5xj1syy"},{"id":"moysjl6j1r2eyex1iezsxtuv79","state":"none","txt":"\u7533\u6292\u8587\u6536\u96c6\u540e\u4ea4\u674e\u627f\u94a2\u5904\u7406","pid":"ljvt71upg2btpuypxhp8rhvth7"},{"id":"m7jn951vhb6lp34eswj773v2ll","state":"open","txt":"\u5e02\u5efa\u59d4\u3001\u603b\u7ad9\u7b49\u95e8\u6237\u7f51\u7ad9\u8d28\u91cf\u65b9\u9762\u4fe1\u606f","pid":"p23x5l9vo65lbfpie4x5xj1syy"},{"id":"k1ats9q28xlai6isslf191r7bt","state":"none","txt":"\u5e9e\u4ed9\u7eea\u6536\u96c6\u540e\u4ea4\u674e\u627f\u94a2\u6536\u6587","pid":"m7jn951vhb6lp34eswj773v2ll"},{"id":"rrsysbwzdzumbtw4b56ob5dz1h","state":"open","txt":"\u4eba\u4e8b\u3001\u8d22\u52a1\u7ba1\u7406","pid":"er1k3bw5be87n1xl62h2rz3xa4"},{"id":"8harhietietws9obelbwx1r2tl","state":"none","txt":"\u5434\u5229\u5a1c\u8d1f\u8d23\u5904\u7406\uff0c\u5177\u4f53\u627f\u529e","pid":"rrsysbwzdzumbtw4b56ob5dz1h"},{"id":"kwl6ntlukbm6obl99dstg6hby4","state":"open","txt":"\u5355\u4f4d\u697c\u5c42\u6587\u5316\u5899\u7b49\u5bf9\u5916\u516c\u793a\u4fe1\u606f\u5efa\u8bbe","pid":"er1k3bw5be87n1xl62h2rz3xa4"},{"id":"dn77bwixpv4asz59hum8s5dqeo","state":"none","txt":"\u5e9e\u4ed9\u7eea\u8d1f\u8d23\uff0c\u5e7f\u544a\u516c\u53f8\u627f\u529e","pid":"kwl6ntlukbm6obl99dstg6hby4"},{"id":"iyb2ul2qh8y172ko8peqisloyf","state":"open","txt":"\u53d1\u6587\u5904\u7406","pid":"er1k3bw5be87n1xl62h2rz3xa4"},{"id":"zh15j7v1lot47j8w622nj8zujv","state":"open","txt":"\u8d77\u8349\u6587\u4ef6\u683c\u5f0f\u6574\u7406\u548c\u5927\u90e8\u5206\u6587\u4ef6\u8d77\u8349\u3001\u683c\u5f0f\u6574\u7406\u3001\u7ea2\u5934\u6587\u4ef6\u5236\u53d1\u548c\u6587\u4ef6\u5e95\u6839\u5b58\u50a8\u4fdd\u7ba1","pid":"iyb2ul2qh8y172ko8peqisloyf"},{"id":"otdpfbyq7f4ew8ygtwhuxf39sh","state":"none","txt":"\u5e9e\u4ed9\u7eea\u4e3b\u8d1f\u8d23\uff0c\u6587\u5370\u5ba4\u914d\u5408\u5236\u5370","pid":"zh15j7v1lot47j8w622nj8zujv"},{"id":"8yzhbpzrvyoxma239xxjpby2eu","state":"open","txt":"\u5404\u7c7b\u4f1a\u8bae\u7ec4\u7ec7\u7ba1\u7406\uff08\u674e\u627f\u94a2\u4e3b\u529e\uff09","pid":"er1k3bw5be87n1xl62h2rz3xa4"},{"id":"44vseliasxd9ttpyv2bb8b7tbq","state":"open","txt":"\u4e0a\u7ea7\u90e8\u95e8\u57f9\u8bad\u3001\u89c2\u6469\u548c\u68c0\u67e5\u4f1a\u52a1","pid":"8yzhbpzrvyoxma239xxjpby2eu"},{"id":"ix7wbkdlvtrw5k8v1s9ljhanwi","state":"none","txt":"\u5e9e\u4ed9\u7eea\u7275\u5934\uff0c\u674e\u627f\u94a2\u7b49\u627f\u529e","pid":"44vseliasxd9ttpyv2bb8b7tbq"},{"id":"hw3du364ltf6dzx7e61zyxy3jw","state":"open","txt":"\u6211\u7ad9\u9762\u5411\u5e02\u573a\u4e3b\u4f53\u7684\u4f1a\u52a1","pid":"8yzhbpzrvyoxma239xxjpby2eu"},{"id":"vh6h3zzxw5rruoa5yj4u9la14e","state":"none","txt":"\u5e9e\u4ed9\u7eea\u7275\u5934\uff0c\u674e\u627f\u94a2\u3001\u8d75\u9ad8\u9633\u3001\u9648\u7687\u81e3\u3001\u5510\u8dc3\u6d2a\u7b49\u627f\u529e","pid":"hw3du364ltf6dzx7e61zyxy3jw"},{"id":"tmo536w6mbz13m5ltuvuyev9k5","state":"open","txt":"\u7ad9\u804c\u5de5\u4f1a\u548c\u7ad9\u52a1\u4f1a\u4f1a\u52a1","pid":"8yzhbpzrvyoxma239xxjpby2eu"},{"id":"w4v676te4kwhx181nnau5n3qwp","state":"none","txt":"\u5e9e\u4ed9\u7eea\u7275\u5934\uff0c\u674e\u627f\u94a2\u627f\u529e","pid":"tmo536w6mbz13m5ltuvuyev9k5"},{"id":"ow8vrwttt58lba6p4bmzotvmxz","state":"open","txt":"\u529e\u4e8b","pid":"er1k3bw5be87n1xl62h2rz3xa4"},{"id":"sv6e3r7osgaug96v2fw7b8ix3r","state":"open","txt":"\u68c0\u67e5\u63a5\u5f85\u4e8b\u9879\uff08\u9152\u5e97\u3001\u5c31\u9910\u3001\u70df\u9152\u7b49\uff09","pid":"ow8vrwttt58lba6p4bmzotvmxz"},{"id":"sbva32pdos8d855wwb5smnddjr","state":"none","txt":"\u5e9e\u4ed9\u7eea\u3001\u674e\u627f\u94a2\u843d\u5b9e","pid":"sv6e3r7osgaug96v2fw7b8ix3r"},{"id":"f9a95jf36351pledt3f8bwjzvf","state":"open","txt":"\u57f9\u8bad\u89c2\u6469\u4e8b\u9879\uff08\u8d44\u6599\u5370\u5236\u3001\u4e0b\u53d1\u901a\u77e5\u3001\u534f\u8c03\u8f66\u8f86\u7b49\uff09","pid":"ow8vrwttt58lba6p4bmzotvmxz"},{"id":"3g2fk9bbbp7jz4jn2uboakwtn8","state":"none","txt":"\u5e9e\u4ed9\u7eea\u7275\u5934\uff0c\u674e\u627f\u94a2\u627f\u529e","pid":"f9a95jf36351pledt3f8bwjzvf"},{"id":"ppp2h2b9hlpet8bbv5i7uzijjh","state":"open","txt":"\u804c\u5de5\u5e74\u5ea6\u8003\u6838\u57fa\u7840\u5de5\u4f5c","pid":"ow8vrwttt58lba6p4bmzotvmxz"},{"id":"73b2nve3oksjx9ml27dbpjzu4l","state":"none","txt":"\u5e9e\u4ed9\u7eea\u3001\u674e\u627f\u94a2\u843d\u5b9e","pid":"ppp2h2b9hlpet8bbv5i7uzijjh"},{"id":"mgxmeamgty4byn3ut7piaehpto","state":"open","txt":"\u9886\u5bfc\u4e34\u65f6\u5b89\u6392\u4e8b\u9879","pid":"ow8vrwttt58lba6p4bmzotvmxz"},{"id":"5gul142e9v2eyf1dibybduldgb","state":"none","txt":"\u6295\u8bc9\u63a5\u5f85\u3001\u4f1a\u8bae\u5ba4\u51c6\u5907\u7b49","pid":"mgxmeamgty4byn3ut7piaehpto"},{"id":"tjovano4dhb7abgh6ptagzuub3","state":"open","txt":"\u5355\u4f4d\u5b9a\u671f\u5370\u5236\u5404\u7c7b\u6253\u5206\u3001\u8bb0\u5206\u3001\u6e05\u5355\u7b49\u8868\u683c","pid":"ow8vrwttt58lba6p4bmzotvmxz"},{"id":"4m12obx7nq5n4dth6tyfo27p6e","state":"none","txt":"\u5e9e\u4ed9\u7eea\u4e3b\u7275\u5934\u843d\u5b9e","pid":"tjovano4dhb7abgh6ptagzuub3"},{"id":"hv9laq8ntn288vfsfbxpsjamfr","state":"open","txt":"\u5355\u4f4d\u7684\u4e34\u65f6\u6027\u3001\u7d27\u6025\u6027\u5de5\u4f5c\u548c\u68c0\u67e5\u7b49\u4e8b\u9879\uff08\u5982\u4e0a\u7ea7\u9700\u8981\u7684\u62a5\u544a\u3001\u62a5\u8868\u3001\u6587\u4ef6\uff09","pid":"ow8vrwttt58lba6p4bmzotvmxz"},{"id":"yuj63nq76tjvnu2iwg2gaxbfbj","state":"none","txt":"\u5e9e\u4ed9\u7eea\u4e3b\u7275\u5934\u843d\u5b9e","pid":"hv9laq8ntn288vfsfbxpsjamfr"},{"id":"9mx3ks9jd6tjqx97yqxqnan7x6","state":"open","txt":"\u5176\u4ed6\u7ecf\u5e38\u6027\u5de5\u4f5c","pid":"er1k3bw5be87n1xl62h2rz3xa4"},{"id":"24xelhbzolnil4a67ur86d7k6y","state":"open","txt":"\u6bcf\u5e74\u5ea6\u3001\u534a\u5e74\u7684\u5730\u533a\u8d28\u91cf\u5206\u6790\u62a5\u544a","pid":"9mx3ks9jd6tjqx97yqxqnan7x6"},{"id":"wf9rqog1pyimlj4m6q9afxit8d","state":"none","txt":"\u5e9e\u4ed9\u7eea\u4e3b\u7275\u5934\uff0c\u7ad9\u4e0a\u5176\u4ed6\u4eba\u5458\u914d\u5408\u5b8c\u6210","pid":"24xelhbzolnil4a67ur86d7k6y"},{"id":"f14gtsw3sx7fy9gj9qnb8drtg7","state":"open","txt":"\u5355\u4f4d\u91cd\u8981\u6027\u603b\u7ed3","pid":"9mx3ks9jd6tjqx97yqxqnan7x6"},{"id":"mhp7ap36s875p3p5xmu3xkawi1","state":"none","txt":"\u5e9e\u4ed9\u7eea\u4e3b\u7275\u5934\u5b8c\u6210","pid":"f14gtsw3sx7fy9gj9qnb8drtg7"},{"id":"knz2iihfp669wnjnobibvumg72","state":"open","txt":"\u5355\u4f4d\u5bf9\u63a5\u5c5e\u5730\u8857\u9053\u3001\u516c\u5b89\u3001\u73af\u536b\u3001\u7535\u4fe1\u3001\u79fb\u52a8\u7b49\u90e8\u95e8\u4e8b\u9879","pid":"9mx3ks9jd6tjqx97yqxqnan7x6"},{"id":"abaei8uldqgs8spil5hx3xpij7","state":"none","txt":"\u529e\u516c\u5ba4\u4eba\u5458\u534f\u52a9\u7ad9\u9886\u5bfc\u5b8c\u6210","pid":"knz2iihfp669wnjnobibvumg72"},{"id":"9x5dbx7niknlsmkhs6vzsjrsm7","state":"open","txt":"\u5355\u4f4d\u996e\u7528\u6c34\u4fdd\u8bc1\u7b49","pid":"9mx3ks9jd6tjqx97yqxqnan7x6"},{"id":"kf29ez64rgsqtkkg94n29e8rvi","state":"none","txt":"\u5e9e\u4ed9\u7eea\u4e3b\u7275\u5934\u5b8c\u6210","pid":"9x5dbx7niknlsmkhs6vzsjrsm7"},{"id":"ousqld1k1qunkgosu78glsqu7k","state":"open","txt":"\u5355\u4f4d\u5e02\u7ea7\u6587\u660e\u7a97\u53e3\u4fdd\u521b\u548c\u6587\u660e\u57ce\u533a\u7eed\u521b","pid":"9mx3ks9jd6tjqx97yqxqnan7x6"},{"id":"ykhr9yxeo25eb41ene2ozw83ko","state":"none","txt":"\u5e9e\u4ed9\u7eea\u4e3b\u7275\u5934\uff0c\u7ad9\u4e0a\u5176\u4ed6\u4eba\u5458\u914d\u5408\u5b8c\u6210","pid":"ousqld1k1qunkgosu78glsqu7k"},{"id":"w534v5r3lrxbk7e8u3sh8vqdp5","state":"open","txt":"\u9879\u76ee\u7ecf\u7406\u8bb0\u5206\u5f55\u5165\u7f51\u4e0a\u7cfb\u7edf","pid":"9mx3ks9jd6tjqx97yqxqnan7x6"},{"id":"xmkbuzskpx7xb3b29x7t5zg9sr","state":"none","txt":"\u5e9e\u4ed9\u7eea\u8d1f\u8d23\u5f55\u5165\u4e0a\u62a5","pid":"w534v5r3lrxbk7e8u3sh8vqdp5"},{"id":"pbap3yjpgjvrvyketx28moiym8","state":"open","txt":"\u4e13\u6280\u4eba\u5458\u7ee7\u7eed\u6559\u80b2\u5b66\u4e60","pid":"9mx3ks9jd6tjqx97yqxqnan7x6"},{"id":"rv3vqbifgz81nommb2d3ffrpem","state":"none","txt":"\u5e9e\u4ed9\u7eea\u8d1f\u8d23\u8ddf\u8e2a\uff0c\u63d0\u9192\u5927\u5bb6\u843d\u5b9e\uff0c\u5e76\u6536\u96c6\u6210\u7ee9\u5408\u683c\u8bc1\uff0c\u4ea4\u5434\u5229\u5a1c\u5b58\u6863\u3002","pid":"pbap3yjpgjvrvyketx28moiym8"},{"id":"oza1w4whzr3lhrmq1fuu18xyo5","state":"none","txt":"\u804c\u5de5\u5e74\u5ea6\u8003\u6838\u3001\u804c\u79f0\u8bc4\u9009\u7b49","pid":"9mx3ks9jd6tjqx97yqxqnan7x6"},{"id":"k773gwmkmumr9xqdmjbma33j52","state":"open","txt":"\u5bf9\u63a5\u533a\u57ce\u4e61\u5efa\u59d4\u3001\u5e02\u603b\u7ad9\u529e\u516c\u5ba4\u7b49\u5176\u4ed6\u90e8\u95e8\u79d1\u5ba4","pid":"er1k3bw5be87n1xl62h2rz3xa4"},{"id":"uvj799dfdn448y49xqq866ganz","state":"none","txt":"\u5206\u7ba1\u526f\u7ad9\u957f\u7275\u5934\uff0c\u529e\u516c\u5ba4\u627f\u529e","pid":"k773gwmkmumr9xqdmjbma33j52"}]}