{"wArr":[11,11],"twArr":[24,12],"maxlv":2,"topicArr":[{"id":"6up9dbvgj579sbf4bd2o7hahfi","state":"open","txt":"\u5730\u65b9","pid":"canvas"},{"id":"f63lfty13yjhbogvk9wstglsi4","state":"none","txt":"1","pid":"6up9dbvgj579sbf4bd2o7hahfi"},{"id":"yz5sjj618miurrb3z3bqswriu4","state":"none","txt":"2","pid":"6up9dbvgj579sbf4bd2o7hahfi"},{"id":"hyg2rhwghlrqoae7gw7iyfbgl9","state":"none","txt":"3","pid":"6up9dbvgj579sbf4bd2o7hahfi"},{"id":"tx7l1r6maniyf5qmt9z4jbnbto","state":"none","txt":"4","pid":"6up9dbvgj579sbf4bd2o7hahfi"},{"id":"mqpymzj9p5eb3h1pdzvbzb45wg","state":"none","txt":"5","pid":"6up9dbvgj579sbf4bd2o7hahfi"},{"id":"5v19wdquuvuxurqe88y5ej424w","state":"none","txt":"","pid":"6up9dbvgj579sbf4bd2o7hahfi"}]}