{"wArr":[11,11,11,11,11,11,11,11,11],"twArr":[108,96,84,72,60,48,36,24,12],"maxlv":9,"topicArr":[{"id":"ssqsilv2b1eu897lsb2qyqgimu","state":"none","txt":"\u5723\u7ecf\u4e5f\u5173\u5fc3\u771f\u7406","pid":"bitfun2erwvnhjkrj5fzkj6qyd"},{"id":"s283r3elm449wi2k5vahsotj7v","state":"none","txt":"\u79d1\u5b66\u5173\u5fc3\u771f\u7406","pid":"bitfun2erwvnhjkrj5fzkj6qyd"},{"id":"bitfun2erwvnhjkrj5fzkj6qyd","state":"close","txt":"\u6574\u5408\u79d1\u5b66\u548c\u5723\u7ecf\u52bf\u5fc5\u8981\u7684","pid":"7f55he8xq5beopazkb7tfn28jq"},{"id":"ku9wrlyyzftgx7yb689sduzdyi","state":"none","txt":"\u73b0\u5728\u6b63\u5728\u8bc1\u660e\u4e0a\u5e1d\u5b58\u5728","pid":"lwjnd3bzel9ayb15ozrkxsgboo"},{"id":"jubqoppvhbzwndm2bg8433a3qg","state":"none","txt":"\u4e4b\u524d\u79d1\u5b66\u8bc1\u660e\u4e0a\u5e1d\u4e0d\u5b58\u5728","pid":"lwjnd3bzel9ayb15ozrkxsgboo"},{"id":"lwjnd3bzel9ayb15ozrkxsgboo","state":"close","txt":"\u79d1\u5b66\u53d8\u5f97\u8c26\u5351\u5e76\u6709\u5f39\u6027","pid":"7f55he8xq5beopazkb7tfn28jq"},{"id":"qpw4wxtgdovnbm4uxvi84rmx77","state":"none","txt":"\u4e0a\u5e1d\u773c\u4e2d\u65f6\u95f4\u771f\u5b9e\u5e76\u4e14\u662f\u76f8\u5bf9\u7684","pid":"pm7o7av29shhhaq6nb3z2xxoqk"},{"id":"2qqxm81g7uyw4a6k71i9hz3t2r","state":"none","txt":"\u4e00\u76f4\u6ca1\u6709\u521b\u9020","pid":"pm7o7av29shhhaq6nb3z2xxoqk"},{"id":"1on6yjqo9eaga9exb424k2rxr9","state":"none","txt":"\u7b2c\u4e03\u5929\u4e4b\u540e\u4e00\u76f4\u4f11\u606f","pid":"pm7o7av29shhhaq6nb3z2xxoqk"},{"id":"pm7o7av29shhhaq6nb3z2xxoqk","state":"close","txt":"\u4e0a\u5e1d\u773c\u4e2d\u7684\u4e00\u5929","pid":"p2xr4nh1hub6oxmlhml6bphgrq"},{"id":"seqbgf59te5a857i5o9go17lw8","state":"none","txt":"\u7b2c\u4e8c\u5929\u6559\u5bfc\u54ea\u4e9b","pid":"canvas"},{"id":"n24vozbppq9q23u233lztmgjl8","state":"none","txt":"\u7b2c\u4e00\u5929\u6559\u5bfc\u90a3\u4e9b","pid":"canvas"},{"id":"14jq4azuumhzxkzf8nvfkh466s","state":"none","txt":"\u7b2c\u4e00\u5929\u6559\u5bfc\u90a3\u4e9b","pid":"5haq32oe2bm5fkelih8d29sdvl"},{"id":"5haq32oe2bm5fkelih8d29sdvl","state":"none","txt":"\u6559\u80b2\u7684\u65f6\u95f4","pid":"p2xr4nh1hub6oxmlhml6bphgrq"},{"id":"mlbwazbst1rga1jjb3ujfdqyy8","state":"none","txt":"\u5f53\u4f5c\u795e\u8bdd","pid":"p2xr4nh1hub6oxmlhml6bphgrq"},{"id":"5iedgtqz2hhbgbssgspjpp2fpx","state":"none","txt":"\u4eba\u7684\u751f\u547d\u5931\u53bb\u7684\u91cd\u8981\u6027","pid":"1xsqnbxg9unfk6r3wudxjtqih4"},{"id":"78gahinem94y6i7a6a7dsv5iua","state":"none","txt":"\u4e0d\u662f6\u5929\u662f6\u4e2a\u5730\u8d28\u5e74\u4ee3","pid":"1xsqnbxg9unfk6r3wudxjtqih4"},{"id":"1xsqnbxg9unfk6r3wudxjtqih4","state":"close","txt":"\u5730\u8d28\u5e74\u4ee3","pid":"p2xr4nh1hub6oxmlhml6bphgrq"},{"id":"fnx5bmwp5r2zgu8v1i5s447l1a","state":"none","txt":"\u5236\u9020\u53e4\u8463","pid":"tvtvw6j23llshbs969rhygs1eg"},{"id":"82uo9vwig1askaxp1elyx6i8ay","state":"none","txt":"\u6d2a\u6c34\u4e4b\u540e","pid":"tvtvw6j23llshbs969rhygs1eg"},{"id":"ua2plhk9lkdlxgmrrbodjhdtzj","state":"none","txt":"\u4e0a\u5e1d\u82b16\u5929\u91cd\u5efa","pid":"1ewjk3w45mbws4b1xzjtj7j71w"},{"id":"1ewjk3w45mbws4b1xzjtj7j71w","state":"close","txt":"\u7b2c\u4e00\u7b2c\u4e8c\u76f8\u9694\u5f88\u4e45","pid":"tvtvw6j23llshbs969rhygs1eg"},{"id":"tvtvw6j23llshbs969rhygs1eg","state":"close","txt":"24\u5c0f\u65f6","pid":"p2xr4nh1hub6oxmlhml6bphgrq"},{"id":"35zlxvbxkiv8t8kfjo2weattu2","state":"none","txt":"\u5e0c\u4f2f\u6765\u6587yom","pid":"p2xr4nh1hub6oxmlhml6bphgrq"},{"id":"p2xr4nh1hub6oxmlhml6bphgrq","state":"close","txt":"\u5929\u7684\u8be0\u91ca","pid":"vgjuyprpdppyobguod36b7k81k"},{"id":"37158bhmptjleai8f35j5dnzyd","state":"none","txt":"\u63cf\u8ff0\u5916\u89c2","pid":"9nhaq12v853qwygvuroxq36iud"},{"id":"9nhaq12v853qwygvuroxq36iud","state":"close","txt":"\u592a\u9633\u56f4\u7ed5\u5730\u7403\u8f6c","pid":"vgjuyprpdppyobguod36b7k81k"},{"id":"olsear9bnhjmar8bw98d6lhj1j","state":"none","txt":"\u63cf\u8ff0\u5916\u89c2","pid":"3j3sk8ouy8a212sj4abdwm6srq"},{"id":"3j3sk8ouy8a212sj4abdwm6srq","state":"close","txt":"\u5730\u7684\u56db\u89d2","pid":"vgjuyprpdppyobguod36b7k81k"},{"id":"vgjuyprpdppyobguod36b7k81k","state":"close","txt":"\u5723\u7ecf\u7684\u8be0\u91ca\u4e5f\u662f\u5728\u6539\u53d8","pid":"1378vpygeprzpt89mfw2d8tbeb"},{"id":"ve42k6llsv6hhjb1s2gypw7yr3","state":"none","txt":"\u79d1\u5b66\u6539\u53d8\u4e86\u5723\u7ecf\u5c31\u63a8\u7ffb\u4e86","pid":"96rbre1t1s7gpvfye5p3kqbnyu"},{"id":"96rbre1t1s7gpvfye5p3kqbnyu","state":"close","txt":"\u4e0d\u80fd\u628a\u5723\u7ecf\u548c\u79d1\u5b66\u7ed1\u5728\u4e00\u8d77","pid":"ztjzss83edagr9elwluhebhxsg"},{"id":"j56m69r4xy5973731okh65pw57","state":"none","txt":"\u5f88\u5c11\u4eba\u76f8\u4fe1\u8fdb\u5316\u8bba","pid":"z1ysn3fuo456idfnvmmfhr4wdv"},{"id":"z1ysn3fuo456idfnvmmfhr4wdv","state":"close","txt":"\u751f\u7269\u5b66\u5728\u6539\u53d8","pid":"ztjzss83edagr9elwluhebhxsg"},{"id":"1oj6spt4j6ar841ih4eu2a1q4q","state":"none","txt":"\u7528\u5404\u79cd\u65b9\u5f0f\u63a8\u6d4b\u5730\u7403\u5e74\u9f84","pid":"pd5xrv8rmrw8blbbpbtmrhaemd"},{"id":"kr2pblxtgbkon2sxpvxxwb5dhp","state":"none","txt":"\u6700\u957f17.5\u4e07\u5e74","pid":"pd5xrv8rmrw8blbbpbtmrhaemd"},{"id":"3mjypbyta9o5sp6zd8zvexh4vs","state":"none","txt":"\u5730\u7403\u6700\u77ed9000\u5e74","pid":"pd5xrv8rmrw8blbbpbtmrhaemd"},{"id":"pd5xrv8rmrw8blbbpbtmrhaemd","state":"close","txt":"\u5730\u8d28\u5b66\u5728\u6539\u53d8","pid":"ztjzss83edagr9elwluhebhxsg"},{"id":"by65sv5ltejusv44wuxhoo54ym","state":"none","txt":"dna\u662f\u4e00\u5957\u8bed\u8a00\u5e76\u975e\u8fdb\u5316","pid":"so5zhykiqhwbm4u1f567npz4jy"},{"id":"so5zhykiqhwbm4u1f567npz4jy","state":"close","txt":"dna\u7684\u53d1\u73b0\u6539\u53d8\u6211\u4eec\u5bf9\u751f\u547d\u7684\u60f3\u6cd5","pid":"ztjzss83edagr9elwluhebhxsg"},{"id":"475d2ajwt3qro99d776z2nnk4v","state":"none","txt":"xy\u51b3\u5b9a\u80ce\u513f\u6027\u522b","pid":"ztjzss83edagr9elwluhebhxsg"},{"id":"yal6k3ypws1jkyew6a7v6g6jbn","state":"none","txt":"\u539f\u5b50\u662f\u6700\u5c0f\u5355\u4f4d","pid":"ztjzss83edagr9elwluhebhxsg"},{"id":"ztjzss83edagr9elwluhebhxsg","state":"close","txt":"\u6709\u4e9b\u66fe\u7ecf\u662f\u79d1\u5b66\uff0c\u73b0\u5728\u63a8\u7ffb","pid":"ozhbaxmua7luaei6t71dybhyra"},{"id":"ozhbaxmua7luaei6t71dybhyra","state":"close","txt":"\u79d1\u5b66\u7684\u7814\u7a76\u4f1a\u6539\u53d8","pid":"1378vpygeprzpt89mfw2d8tbeb"},{"id":"1378vpygeprzpt89mfw2d8tbeb","state":"close","txt":"\u5316\u89e3\u51b2\u7a81\u65b9\u6cd5","pid":"7f55he8xq5beopazkb7tfn28jq"},{"id":"7f55he8xq5beopazkb7tfn28jq","state":"close","txt":"\u6574\u5408","pid":"sim7nbuoubtanwdss8t1vbxqld"},{"id":"z3j11bq6z2qn8dpqehbqd4a58r","state":"none","txt":"\u5c06\u5723\u7ecf\u4e0e\u5176\u4ed6\u7ecf\u4e66\u5e76\u5217\u53d8\u6210\u4ef7\u503c\u89c2","pid":"13k2736ntiwo3j55o5e9kbdwp5"},{"id":"b9ndhgn3uryldqjj1t3b4wbr2v","state":"none","txt":"\u5723\u7ecf\u771f\u5047\u96be\u8fa8","pid":"13k2736ntiwo3j55o5e9kbdwp5"},{"id":"mbd5spwxiw5rzoa81x1r3qlmr7","state":"none","txt":"\u65e0\u6cd5\u5206\u8fa8\u6559\u5bfc\u548c\u4e8b\u5b9e","pid":"13k2736ntiwo3j55o5e9kbdwp5"},{"id":"13k2736ntiwo3j55o5e9kbdwp5","state":"close","txt":"\u5c06\u521b\u4e16\u7eaa\u5f53\u4f5c\u795e\u8bdd\u5e76\u975e\u53f2\u8bd7\u7684\u540e\u679c","pid":"je6mpf7rqzynu1bmxtorigd7av"},{"id":"2thszv1p6nnfzaud7h3prk2zdn","state":"none","txt":"\u601d\u60f3\u6839\u6e90\u5e0c\u814a\u601d\u60f3\u7684\u5f71\u54cd","pid":"je6mpf7rqzynu1bmxtorigd7av"},{"id":"sxf8whgnghq87txu5u3yhp4abq","state":"none","txt":"\u79d1\u5b66\u8c08\u4e8b\u5b9e\uff0c\u5723\u7ecf\u8c08\u4ef7\u503c\u89c2","pid":"qv96wqxo9qhyj442zzzqdmozxd"},{"id":"jnmexj18nlg7xbnqltian5up5p","state":"none","txt":"\u5723\u7ecf\u91cd\u89c6\u9053\u5fb7\u548c\u8d85\u81ea\u7136\u7684\u771f\u7406","pid":"qv96wqxo9qhyj442zzzqdmozxd"},{"id":"vpxy7zfkjj5d7ejq3gvb3y5hvh","state":"none","txt":"\u79d1\u5b66\u91cd\u89c6\u7269\u8d28\u548c\u81ea\u7136\u754c","pid":"qv96wqxo9qhyj442zzzqdmozxd"},{"id":"qv96wqxo9qhyj442zzzqdmozxd","state":"close","txt":"\u5c3d\u53ef\u80fd\u5206\u5f00","pid":"je6mpf7rqzynu1bmxtorigd7av"},{"id":"je6mpf7rqzynu1bmxtorigd7av","state":"close","txt":"\u9694\u79bb","pid":"sim7nbuoubtanwdss8t1vbxqld"},{"id":"3eoxbn6tu3i2eogke1yb558m5p","state":"none","txt":"\u5e76\u975e\u629b\u5f03\u7406\u6027\u624d\u80fd\u63a5\u53d7\u5723\u7ecf","pid":"f585b55pbdkx4df9ohyoh1beqw"},{"id":"p52w3exaz1l8in9apm95bbva2u","state":"none","txt":"\u5426\u8ba4\u6216\u8005\u5168\u76d8\u63a5\u53d7\u90fd\u662f\u611a\u8822\u7684","pid":"daarawxua77f5mjs2b4fem9bzb"},{"id":"pblbl44t27k6b3rktou5x47knm","state":"none","txt":"\u4e24\u65b9\u9762\u5f7c\u6b64\u4e0d\u80fd\u63a5\u53d7\u5bf9\u65b9","pid":"daarawxua77f5mjs2b4fem9bzb"},{"id":"daarawxua77f5mjs2b4fem9bzb","state":"close","txt":"\u65e0\u77e5\u7684\u57fa\u7763\u5f92\uff0c\u903c\u4eba\u505a\u51fa\u9009\u62e9","pid":"f585b55pbdkx4df9ohyoh1beqw"},{"id":"f585b55pbdkx4df9ohyoh1beqw","state":"close","txt":"\u5426\u8ba4","pid":"sim7nbuoubtanwdss8t1vbxqld"},{"id":"sim7nbuoubtanwdss8t1vbxqld","state":"close","txt":"\u7528\u6574\u5408\u7684\u65b9\u5f0f\u9762\u5bf9\u5206\u6b67","pid":"f8hv17wi1nmlspa875ppvz8v28"},{"id":"onxlf7igxbthre4efgqfbwubyj","state":"none","txt":"\u5148\u8c08\u8bba\u95ee\u9898\uff0c\u53ef\u80fd\u9519\u8fc7\u4fe1\u606f","pid":"mip21hqnq6uougex92svklna9v"},{"id":"7si6zkp5ka2j6qdyuq2bvfjqpw","state":"none","txt":"\u5148\u4e86\u89e3\u4fe1\u606f\uff0c\u7136\u540e\u89e3\u51b3\u95ee\u9898","pid":"mip21hqnq6uougex92svklna9v"},{"id":"mip21hqnq6uougex92svklna9v","state":"close","txt":"\u5904\u7406\u8bfb\u5723\u7ecf\u548c\u95ee\u9898\u7684\u539f\u5219","pid":"ha3iui9a2wys85mk5khmyizek5"},{"id":"7ktil39y21btu3vd488ithap7r","state":"none","txt":"\u6d2a\u6c34\u7684\u8303\u56f4","pid":"nhoo7fbv4lier51xehpl3hjak7"},{"id":"okx2i12d3exjkuao1jv4vedbw1","state":"none","txt":"\u739b\u571f\u6492\u62c9969","pid":"h2jo6v963s2w9bifoh2bufr3oe"},{"id":"h2jo6v963s2w9bifoh2bufr3oe","state":"close","txt":"\u6d2a\u6c34\u4e4b\u524d\u4eba\u7c7b\u7684\u5bff\u547d","pid":"nhoo7fbv4lier51xehpl3hjak7"},{"id":"rvwwuz1h98tavfpu42okve8uir","state":"none","txt":"\u521b\u9020\u8bba\u6b63\u786e","pid":"i3e5i8q6u41hqwmf61db55o29q"},{"id":"gvdl6addw38qlf8khbsqbjva8l","state":"none","txt":"\u8fdb\u5316\u8bba\u6b63\u786e","pid":"i3e5i8q6u41hqwmf61db55o29q"},{"id":"i3e5i8q6u41hqwmf61db55o29q","state":"close","txt":"\u52a8\u7269\u548c\u4eba\u7684\u8d77\u6e90","pid":"nhoo7fbv4lier51xehpl3hjak7"},{"id":"bhripmeg2bvifepsed34g5bmyx","state":"none","txt":"\u4eba\u5728\u6700\u540e\u51fa\u73b0","pid":"9pj3dqomqydqbhe1hqjtyhfb94"},{"id":"45zh35ibqrr734fvibbagfjhl1","state":"none","txt":"\u6d77\u4e2d\u6bd4\u9646\u5730\u73b0\u6709\u751f\u7269","pid":"9pj3dqomqydqbhe1hqjtyhfb94"},{"id":"9pj3dqomqydqbhe1hqjtyhfb94","state":"close","txt":"\u6240\u4ee5\u79d1\u5b66\u7684\u770b\u6cd5\u548c\u521b\u4e00\u81f4","pid":"mb9pq7em6ronj4rilw4nd7qjaj"},{"id":"qh8ulo1ndkdqyr6dh674nxubdk","state":"none","txt":"\u663e\u9732\u65e5\u6708\u661f\u8fb0","pid":"9kfkip5hhj1q9kxb7x3a2pkrny"},{"id":"a22bjq3xjt7l3evqok6m4w5b6n","state":"none","txt":"\u6e05\u9664\u4e91\u96fe","pid":"9kfkip5hhj1q9kxb7x3a2pkrny"},{"id":"efz7or44n1tik63n67o61s6pn5","state":"none","txt":"\u690d\u7269\u51fa\u73b0\u4e4b\u540e\u8fdb\u884c\u5149\u5408\u4f5c\u7528","pid":"9kfkip5hhj1q9kxb7x3a2pkrny"},{"id":"9kfkip5hhj1q9kxb7x3a2pkrny","state":"close","txt":"\u5149\u51fa\u73b0\u50cf\u4e00\u5c42\u8584\u4e91","pid":"rlhjbb8kbhavu1quib3ro629yt"},{"id":"fvwzj2dof1x68ujywxidieutpf","state":"none","txt":"\u79d1\u5b66\u8bc1\u660e","pid":"51muz8qbsshdg6nmu3ijw2554n"},{"id":"zboziqpg98nowftis7mplp7d89","state":"none","txt":"\u521b2\u5168\u5730\u88ab\u4e91\u96fe\u906e\u853d","pid":"51muz8qbsshdg6nmu3ijw2554n"},{"id":"51muz8qbsshdg6nmu3ijw2554n","state":"close","txt":"\u5730\u7403\u8d77\u521d\u7531\u4e00\u5c42\u539a\u4e91\u7b3c\u7f69","pid":"rlhjbb8kbhavu1quib3ro629yt"},{"id":"qaqk56wj5tt4qzjrw3ubausp1x","state":"none","txt":"\u79d1\u5b66\u8ba4\u4e3a\u65e5\u6708\u661f\u8fb0\u5728\u690d\u7269\u51fa\u73b0\u4e4b\u540e","pid":"rlhjbb8kbhavu1quib3ro629yt"},{"id":"rlhjbb8kbhavu1quib3ro629yt","state":"close","txt":"\u6709\u4e00\u70b9\u4e0d\u540c","pid":"mb9pq7em6ronj4rilw4nd7qjaj"},{"id":"bojurjr1pbpdibyf9mpnynverq","state":"none","txt":"\u79d1\u5b66\u548c\u5723\u7ecf\u4e00\u81f4","pid":"mb9pq7em6ronj4rilw4nd7qjaj"},{"id":"mb9pq7em6ronj4rilw4nd7qjaj","state":"close","txt":"\u5730\u7403\u7684\u5e74\u9f84\u521b\u9020\u7684\u987a\u5e8f","pid":"nhoo7fbv4lier51xehpl3hjak7"},{"id":"khztmiby8ee5kn1twx2vdb5bdj","state":"none","txt":"\u521b\u4e16\u7eaa6\u5929","pid":"l6jnlsqypnrz7sq7d7vx5vzuzk"},{"id":"k8o5bw5ea3nvomye1e2s1ufk4n","state":"none","txt":"\u5730\u8d28\u5b66\u5bb642.5\u4ebf\u5e74","pid":"l6jnlsqypnrz7sq7d7vx5vzuzk"},{"id":"l6jnlsqypnrz7sq7d7vx5vzuzk","state":"close","txt":"\u521b\u9020\u7684\u901f\u5ea6","pid":"nhoo7fbv4lier51xehpl3hjak7"},{"id":"nhoo7fbv4lier51xehpl3hjak7","state":"close","txt":"\u91cd\u8981\u7684\u95ee\u9898","pid":"ha3iui9a2wys85mk5khmyizek5"},{"id":"6yikeaoybl9aor8pb7mgn1o9rd","state":"none","txt":"\u50ac\u6bdb\u6c42\u75b5\u7684\u95ee\u9898","pid":"ha3iui9a2wys85mk5khmyizek5"},{"id":"w1o36opz8zute5xxzejvxrhmnu","state":"none","txt":"\u79d1\u5b66\u4e0d\u63a5\u89e6\u8d85\u81ea\u7136\u7684\u4e8b\u60c5","pid":"ha3iui9a2wys85mk5khmyizek5"},{"id":"ha3iui9a2wys85mk5khmyizek5","state":"close","txt":"\u79d1\u5b66\u548c\u5723\u7ecf\u4e4b\u95f4\u7684\u5173\u7cfb","pid":"f8hv17wi1nmlspa875ppvz8v28"},{"id":"a1vx2pm5j4ztfabdkp9ngrs2lu","state":"none","txt":"\u5b9e\u9645\u64cd\u4f5c\u8981\u7406\u6027\u7684\u7edf\u7b79\u5206\u6790","pid":"e5unjk3tv5fgagb2frrv2yy6jw"},{"id":"z5qq2ajr6vtnvtq1ieth5sxz61","state":"none","txt":"\u666e\u901a\u4eba\u591f\u4e86\uff0c\u771f\u5b9e\u64cd\u4f5c\u9700\u8981\u8be6\u7ec6","pid":"e5unjk3tv5fgagb2frrv2yy6jw"},{"id":"e5unjk3tv5fgagb2frrv2yy6jw","state":"close","txt":"\u666e\u901a\u4eba\u4e86\u89e3\u4e0e\u4e13\u4e1a\u64cd\u4f5c","pid":"lbodax5ka1bhpwbagbplwm18ja"},{"id":"v4jaksqxgv514l84qb7tkh2gya","state":"none","txt":"\u88c5\u6f62","pid":"g29qjmz5jong5qg5giiwb83ltx"},{"id":"l191baav23kjhd5yl9zl77iztj","state":"none","txt":"\u6c34\u6ce5\u5de5","pid":"g29qjmz5jong5qg5giiwb83ltx"},{"id":"6kfdqf16obhns4jz1bpx21xf11","state":"none","txt":"\u7535\u5de5","pid":"g29qjmz5jong5qg5giiwb83ltx"},{"id":"9u35k1fkutgsy5hn3xzvl9kdfy","state":"none","txt":"\u6c34\u7535\u5de5\u88c5\u81ea\u6765\u6c34\u548c\u6392\u6c34","pid":"g29qjmz5jong5qg5giiwb83ltx"},{"id":"ubum7bp4yekb58oe7wtz8x3s7j","state":"none","txt":"\u6728\u5de5\u88c5\u95e8\u7a97","pid":"g29qjmz5jong5qg5giiwb83ltx"},{"id":"wn1vg19kq1gqd8abot3hbi1jq1","state":"none","txt":"\u5de5\u4eba\u6765\u780c\u7816\u5934","pid":"g29qjmz5jong5qg5giiwb83ltx"},{"id":"g29qjmz5jong5qg5giiwb83ltx","state":"close","txt":"\u7ae5\u4e667\u6b65\u63cf\u8ff0\u76d6\u623f\u5b50","pid":"lbodax5ka1bhpwbagbplwm18ja"},{"id":"lbodax5ka1bhpwbagbplwm18ja","state":"close","txt":"\u521b\u4e00\u7ae0\u63cf\u8ff0\u7b80\u5355\u7684\u7528\u610f","pid":"f8hv17wi1nmlspa875ppvz8v28"},{"id":"1zydbyod53fua7qelmdru5bhga","state":"none","txt":"\u7b80\u5355\u53ef\u4fe1","pid":"ztqzxu7yps2kd5heqbgeznvhqd"},{"id":"kdbds86z8bhriz9qwl6b5z14nt","state":"none","txt":"\u590d\u6742\u8be1\u5f02","pid":"ztqzxu7yps2kd5heqbgeznvhqd"},{"id":"ztqzxu7yps2kd5heqbgeznvhqd","state":"close","txt":"\u4e0e\u5df4\u6bd4\u4f26\u53f2\u8bd7\u6bd4\u8f83","pid":"as5477tgipfl3dq4oq1ked2h25"},{"id":"3gt4ivf8hs3vmbqqaoawfbgqza","state":"none","txt":"10\u4ee3\u8868\u5b8c\u6574","pid":"as5477tgipfl3dq4oq1ked2h25"},{"id":"pzjwpzfbyo2af9z64uidze6ixg","state":"none","txt":"\u6700\u540e\u4e09\u53e5\uff0c\u6bcf\u53e5\u90fd\u662f7\u4e2a\u5b57","pid":"z2aeux5yzu2evt7w1eat2qebx2"},{"id":"wtso1n5th3qjse69hdft3r8o72","state":"none","txt":"7\u5929","pid":"z2aeux5yzu2evt7w1eat2qebx2"},{"id":"ghs7x5hwzruwonibzv7r5oov23","state":"none","txt":"7\u6b21\u5f88\u6ee1\u610f","pid":"z2aeux5yzu2evt7w1eat2qebx2"},{"id":"z2aeux5yzu2evt7w1eat2qebx2","state":"close","txt":"7\u4ee3\u8868\u5b8c\u7f8e","pid":"as5477tgipfl3dq4oq1ked2h25"},{"id":"p1uobwqhbdn5nyerjm46fb7i2u","state":"none","txt":"\u4e09\u6b21\u8d50\u798f","pid":"8ijxabz3jn624h5d7v4s9hae6v"},{"id":"p9polsvzzb1rxbbf817ux1mxba","state":"none","txt":"\u4e09\u6b21\u521b\u9020","pid":"8ijxabz3jn624h5d7v4s9hae6v"},{"id":"fmw4uhr97bmqnf2vzrh7ppxkol","state":"none","txt":"\u4e09\u6b21\u65e0\u4e2d\u751f\u6709","pid":"8ijxabz3jn624h5d7v4s9hae6v"},{"id":"8ijxabz3jn624h5d7v4s9hae6v","state":"close","txt":"3\u4ee3\u8868\u4e0a\u5e1d","pid":"as5477tgipfl3dq4oq1ked2h25"},{"id":"as5477tgipfl3dq4oq1ked2h25","state":"close","txt":"\u521b\u4e00\u7ae0\u7684\u6570\u5b57\u5b8c\u7f8e","pid":"f8hv17wi1nmlspa875ppvz8v28"},{"id":"t6ogrlsxien1vaft4w8xmvm6eh","state":"none","txt":"\u7b2c\u4e03\u5929\u4f11\u606f","pid":"mmznj1dgboa9gwxbakk4zfpqoo"},{"id":"is6b7v4pvxvqpdlngn1n8bw7nb","state":"none","txt":"\u52a8\u7269\u4eba\u7c7b","pid":"rreyhv6g9tomlw4aeqxu2oquvj"},{"id":"rreyhv6g9tomlw4aeqxu2oquvj","state":"close","txt":"\u6d77\u6d0b\u9646\u5730\uff08\u690d\u7269\uff09","pid":"upu5kdogtefivzagmq1b9ka1gk"},{"id":"tdm1iiyjxkeihzpfz1vv28qvh9","state":"none","txt":"\u9e1f\u3001\u9c7c","pid":"yma6umy8wfebb3eqpfglyoambu"},{"id":"yma6umy8wfebb3eqpfglyoambu","state":"close","txt":"\u5929\u5730","pid":"upu5kdogtefivzagmq1b9ka1gk"},{"id":"1xulrhf8eyxwfmxpqxedk4hysg","state":"none","txt":"\u65e5\u6708\u661f\u8fb0","pid":"89yimq5di7syuwbykikrxsu4uq"},{"id":"89yimq5di7syuwbykikrxsu4uq","state":"close","txt":"\u5149\u660e\u9ed1\u6697","pid":"upu5kdogtefivzagmq1b9ka1gk"},{"id":"6b2ohl7l1asikbk72e65rx5erw","state":"none","txt":"\u5bf9\u6bd4\u5e26\u6765\u53d8\u5316","pid":"upu5kdogtefivzagmq1b9ka1gk"},{"id":"upu5kdogtefivzagmq1b9ka1gk","state":"close","txt":"\u5934\u4e09\u5929\u6709\u660e\u663e\u5bf9\u6bd4","pid":"mmznj1dgboa9gwxbakk4zfpqoo"},{"id":"ya7ymml4yjomnqq47z2jt26sht","state":"none","txt":"\u5148\u521b\u9020\u73af\u5883\u518d\u521b\u9020\u751f\u7269\u8fdb\u9a7b\u73af\u5883","pid":"l7vkzof973uiv1ztvy3iv82ta1"},{"id":"s5aoalwgdbxzpzeyyvj34f17fk","state":"none","txt":"\u4e09\u5929\u521b\u9020\u751f\u7269","pid":"l7vkzof973uiv1ztvy3iv82ta1"},{"id":"9entgideuvvme1iaj5frlsx6my","state":"none","txt":"\u4e09\u5929\u521b\u9020\u73af\u5883","pid":"l7vkzof973uiv1ztvy3iv82ta1"},{"id":"l7vkzof973uiv1ztvy3iv82ta1","state":"close","txt":"\u516d\u5929\u53ef\u4ee5\u5206\u6210\u4e09\u5929\u4e09\u5929","pid":"mmznj1dgboa9gwxbakk4zfpqoo"},{"id":"nbxbwb1m5xj95wb9h1oj9zekoe","state":"none","txt":"\u8d77\u521d\u5730\u4e0a\u65e0\u4eba\u5c45\u4f4f","pid":"mmznj1dgboa9gwxbakk4zfpqoo"},{"id":"7ino9bj5j6quq1bykfkwmnqx34","state":"none","txt":"\u521b\u9020\u4e95\u7136\u6709\u5e8f\uff0c\u5947\u5999\u65e0\u6bd4","pid":"mmznj1dgboa9gwxbakk4zfpqoo"},{"id":"mmznj1dgboa9gwxbakk4zfpqoo","state":"close","txt":"\u521b\u4e00\u7ae0\u7684\u7ed3\u6784\u6e05\u6670","pid":"f8hv17wi1nmlspa875ppvz8v28"},{"id":"ozh7phz78h29rurn736sa4q69x","state":"none","txt":"\u4eba\u7c7b\u53ea\u80fd\u5236\u9020\u4e0d\u80fd\u521b\u9020","pid":"n75p762wngxukfmwz4tt8utwdf"},{"id":"3fszspf5bzw6eqm2pyuavm28tq","state":"none","txt":"\u5176\u4ed6\u65f6\u5019\u7528\u5236\u9020","pid":"n75p762wngxukfmwz4tt8utwdf"},{"id":"hpqb7tigqh4s4b2azf5w6byzi8","state":"none","txt":"\u9020\u7269\u8d28\uff0c\u751f\u7269\uff0c\u4eba\u7684\u65f6\u5019","pid":"n75p762wngxukfmwz4tt8utwdf"},{"id":"s947ptgxnpnhdmkaylr1eh4tz2","state":"none","txt":"\u5728\u521b\u4e16\u7eaa\u4e2d\u53ea\u51fa\u73b0\u4e09\u6b21","pid":"n75p762wngxukfmwz4tt8utwdf"},{"id":"vzazopdtlw3knn7yuj3nfd2kzp","state":"none","txt":"\u4ece\u65e0\u5230\u6709","pid":"n75p762wngxukfmwz4tt8utwdf"},{"id":"n75p762wngxukfmwz4tt8utwdf","state":"close","txt":"bara\u521b\u9020","pid":"89rg4yydgs1vavrx3dow7x2jao"},{"id":"89rg4yydgs1vavrx3dow7x2jao","state":"close","txt":"\u521b\u9020\u548c\u5236\u9020\u662f\u4e0d\u540c\u7684","pid":"kdmkzev36z5nj3epwmyj7rpb8g"},{"id":"3o6u341mrzblmyev71osbkfu88","state":"none","txt":"\u4e3b\u8c13\u5bbe\u4e09\u4e2a\u90e8\u5206","pid":"fxytu8k4ovbnjrfkybb7iehrwt"},{"id":"fxytu8k4ovbnjrfkybb7iehrwt","state":"close","txt":"\u53e5\u5b50\u7b80\u5355","pid":"kdmkzev36z5nj3epwmyj7rpb8g"},{"id":"ewxpqbkp7dedg1gbtwg3ropb2t","state":"none","txt":"\u4f8b\u5b50\uff1a\u7231\u56e0\u65af\u5766\u89e3\u91ca\u76f8\u5bf9\u8bba","pid":"erwvbnjtk1fskibu5z9rs9ns3n"},{"id":"4lff6gmbom1dppbn2il2ww37bl","state":"none","txt":"\u7b80\u5355\u7684\u6587\u5b57\u662f\u7edd\u9876\u806a\u660e\u7684\u4eba\u624d\u80fd\u5199\u51fa\u7684","pid":"erwvbnjtk1fskibu5z9rs9ns3n"},{"id":"erwvbnjtk1fskibu5z9rs9ns3n","state":"close","txt":"\u7b80\u5355\u6240\u4ee5\u771f\u5b9e","pid":"nsvvnwwoiistb1hvds3649nd16"},{"id":"vg9o6yoxrxzf5up6kosavbkn6u","state":"none","txt":"\u5c0f\u5b69\u5b50\u90fd\u80fd\u770b\u61c2","pid":"zqbnwfzxxy755xr27tm3ttd4m6"},{"id":"x1ztss8j2ehdp2kbdunj8r4hb8","state":"none","txt":"\u4e0a\u5e1d\u8981\u8ba9\u6bcf\u4e2a\u4eba\u90fd\u80fd\u8bfb\u61c2\uff0c\u6240\u4ee5\u5199\u7684\u6d45\u663e","pid":"zqbnwfzxxy755xr27tm3ttd4m6"},{"id":"zqbnwfzxxy755xr27tm3ttd4m6","state":"close","txt":"\u76ee\u7684","pid":"nsvvnwwoiistb1hvds3649nd16"},{"id":"sa7x1w3q9o41rdsszknkykaqx9","state":"none","txt":"\u8ba1\u7b97\u51fa\u591a\u5c11\u4eba\u770b\u5f97\u61c2","pid":"kd3tljei4jhz6mxxnu817oz6rg"},{"id":"jgh8wtysj2i1azmd83kq3o67uv","state":"none","txt":"\u628a\u53e5\u5b50\u6570\u548c\u97f3\u8282\u8f93\u5165","pid":"kd3tljei4jhz6mxxnu817oz6rg"},{"id":"zpi2ldy7bjzee9g4k217nbl2dk","state":"none","txt":"\u8ff7\u96fe\u6307\u6570","pid":"kd3tljei4jhz6mxxnu817oz6rg"},{"id":"kd3tljei4jhz6mxxnu817oz6rg","state":"close","txt":"\u4f5c\u5bb6\u5199\u4f5c\u8981\u9488\u5bf9\u7279\u5b9a\u7684\u8bfb\u8005","pid":"nsvvnwwoiistb1hvds3649nd16"},{"id":"ktuiis34e6mr1hljturfrqab2k","state":"none","txt":"\u5b57\u6839\u53ea\u670976\u4e2a","pid":"hzkd75grgzfbxiuqezb6r48v5m"},{"id":"rvb4ur2oswmb66ipoob3tkjo8n","state":"none","txt":"\u6240\u6709\u7ae0\u8282\u4e2d\u6700\u5bb9\u6613\u7ffb\u8bd1\u7684","pid":"hzkd75grgzfbxiuqezb6r48v5m"},{"id":"hzkd75grgzfbxiuqezb6r48v5m","state":"close","txt":"\u5728\u6240\u6709\u7684\u8bed\u8a00\u4e2d\u90fd\u6709\u8fd9\u4e9b\u5b57","pid":"nsvvnwwoiistb1hvds3649nd16"},{"id":"nsvvnwwoiistb1hvds3649nd16","state":"close","txt":"\u7528\u8bcd\u7b80\u5355","pid":"kdmkzev36z5nj3epwmyj7rpb8g"},{"id":"79ypmbibku6senrjtkb6dr1id8","state":"none","txt":"\u5bb6\u755c\uff0c\u730e\u7269\uff0c\u91ce\u517d","pid":"b115mrit4zntg68izb25s49uet"},{"id":"b115mrit4zntg68izb25s49uet","state":"close","txt":"\u4e09\u79cd\u52a8\u7269","pid":"vanb93b9h6wuohk3gmjihfeoto"},{"id":"nzx29onpxw88as26m2jmfqk7ud","state":"none","txt":"\u9752\u8349\uff0c\u83dc\u852c\uff0c\u6811\u6728","pid":"bqmmglzz7bwstt2tbobo86g73m"},{"id":"bqmmglzz7bwstt2tbobo86g73m","state":"close","txt":"\u4e09\u79cd\u690d\u7269","pid":"vanb93b9h6wuohk3gmjihfeoto"},{"id":"vanb93b9h6wuohk3gmjihfeoto","state":"close","txt":"\u6839\u636e\u4e8b\u7269\u548c\u4eba\u4e4b\u95f4\u7684\u5173\u7cfb\u6765\u5206\u7c7b","pid":"kdmkzev36z5nj3epwmyj7rpb8g"},{"id":"i3ktltwn4i2qbb1pgzy6xo8sgh","state":"none","txt":"\u6ca1\u4eba\u80fd\u591f\u770b\u5f97\u61c2","pid":"b5411t1mg53b3kfymji1mjgm8i"},{"id":"b189b96vjwoqfs4eowmfsi68l5","state":"none","txt":"\u5149\u7684\u79d1\u5b66\u516c\u5f0f","pid":"b5411t1mg53b3kfymji1mjgm8i"},{"id":"b5411t1mg53b3kfymji1mjgm8i","state":"close","txt":"\u4f8b\u5b50","pid":"57srttze2tynbe99ujnbqyl22a"},{"id":"57srttze2tynbe99ujnbqyl22a","state":"close","txt":"\u4e0d\u662f\u7528\u79d1\u5b66\u672f\u8bed\u5199\u6210\u7684","pid":"kdmkzev36z5nj3epwmyj7rpb8g"},{"id":"kdmkzev36z5nj3epwmyj7rpb8g","state":"close","txt":"\u521b\u4e00\u7ae0\u7684\u9063\u8bcd\u7528\u53e5\u7b80\u5355","pid":"f8hv17wi1nmlspa875ppvz8v28"},{"id":"8ybwwpxyibb5kp7kb9wbfdmbxh","state":"none","txt":"\u4e09\u4f4d\u4e00\u4f53\u6c38\u8fdc\u638c\u7ba1\u5b87\u5b99","pid":"xkfetq8j9kdt289phrukfbpoj5"},{"id":"75yippqkbyx5j44s4eo351uztt","state":"none","txt":"\u5723\u7ecf\u7684\u89c2\u70b9","pid":"xkfetq8j9kdt289phrukfbpoj5"},{"id":"xkfetq8j9kdt289phrukfbpoj5","state":"close","txt":"\u4e09\u5408\u4e00\u8bba","pid":"ksumra31z7mnh1bzqobv178vbz"},{"id":"wg92bigj3a3j1ni6epzgmdbuvz","state":"none","txt":"\u4e07\u6709\u6982\u795e\u8bba","pid":"1s63rb9su4673de7x9ura3aopt"},{"id":"8e98tatsstdyq5gt9w93san5vj","state":"none","txt":"\u51e1\u7269\u90fd\u662f\u795e","pid":"1s63rb9su4673de7x9ura3aopt"},{"id":"1s63rb9su4673de7x9ura3aopt","state":"close","txt":"\u6cdb\u795e\u8bba","pid":"ksumra31z7mnh1bzqobv178vbz"},{"id":"xm9p8nzvgf8nz57r3i693srfdd","state":"none","txt":"\u7269\u8d28\u548c\u7075\u9b42\u672c\u8d28\u662f\u4e00\u6837\u7684","pid":"smnforyq1l9mh2a1j9gkritzgd"},{"id":"smnforyq1l9mh2a1j9gkritzgd","state":"close","txt":"\u4e00\u5143\u8bba","pid":"ksumra31z7mnh1bzqobv178vbz"},{"id":"n9o8soajxfxdvjrxtfmmqy3p7m","state":"none","txt":"\u53ea\u6709\u7075\u624d\u771f\u5b9e","pid":"v7a9sbjw4v5bbjxfsy7qxslz7b"},{"id":"v7a9sbjw4v5bbjxfsy7qxslz7b","state":"close","txt":"\u795e\u79d8\u8bba","pid":"ksumra31z7mnh1bzqobv178vbz"},{"id":"oy3blom2i11w4phhi8bbb67rsl","state":"none","txt":"\u76f8\u4fe1\u53ea\u6709\u7269\u8d28\u624d\u771f\u5b9e","pid":"9ap28svotbbph7gsrstobz5wt3"},{"id":"9ap28svotbbph7gsrstobz5wt3","state":"close","txt":"\u552f\u7269\u8bba","pid":"ksumra31z7mnh1bzqobv178vbz"},{"id":"kovutm7wzhgfvb16b8ukxhu72w","state":"none","txt":"\u76f8\u4fe1\u7406\u6027\u662f\u795e","pid":"exwixfznggjh25pbzm8nprlai5"},{"id":"exwixfznggjh25pbzm8nprlai5","state":"close","txt":"\u552f\u7406\u8bba","pid":"ksumra31z7mnh1bzqobv178vbz"},{"id":"dbqp9od9sdi9bg66bo6io7xnmz","state":"none","txt":"\u76f8\u4fe1\u4eba\u662f\u795e","pid":"by1u16rsj8ebnrf42xed2xrq1q"},{"id":"by1u16rsj8ebnrf42xed2xrq1q","state":"close","txt":"\u4eba\u672c\u8bba","pid":"ksumra31z7mnh1bzqobv178vbz"},{"id":"zfbhgk23mi9m77tfjpbxqddftp","state":"none","txt":"\u4fe1\u5949\u81ea\u6211\u51b3\u5b9a\u548c\u81ea\u6211\u80af\u5b9a","pid":"84svimpi5bblilb577piggb56n"},{"id":"min9863v53dbfm3r6u5uf1fqlf","state":"none","txt":"\u76f8\u4fe1\u7ecf\u9a8c\u662f\u795e","pid":"84svimpi5bblilb577piggb56n"},{"id":"84svimpi5bblilb577piggb56n","state":"close","txt":"\u5b58\u5728\u8bba","pid":"ksumra31z7mnh1bzqobv178vbz"},{"id":"vm2xebb4a5az6rhtdwnu5wyr99","state":"none","txt":"\u548c\u5723\u7ecf\u7684\u89c2\u70b9\u53ea\u5dee\u4e00\u6b65","pid":"s4lqry2qb36q6xz1fx6dz9uwim"},{"id":"a1971h9r9qeu927s2tgraan4we","state":"none","txt":"\u795e\u521b\u9020\u4e16\u754c\u5e76\u638c\u63a7\u4e16\u754c","pid":"s4lqry2qb36q6xz1fx6dz9uwim"},{"id":"s4lqry2qb36q6xz1fx6dz9uwim","state":"close","txt":"\u6709\u795e\u8bba","pid":"ksumra31z7mnh1bzqobv178vbz"},{"id":"8aqpxnwovi6s4kmq8a9y5jb37l","state":"none","txt":"\u4f8b\u5982\uff1a\u624b\u8868\u4e0a\u5f26","pid":"mhj4li41ri7zdywaa52uzwyb7x"},{"id":"ob214g89rwu4xrr1a8zgpiqd4i","state":"none","txt":"\u795e\u521b\u9020\u4e86\u5b87\u5b99\uff0c\u4f46\u662f\u73b0\u5728\u65e0\u6cd5\u638c\u63a7\u81ea\u5df1\u7684\u521b\u9020","pid":"mhj4li41ri7zdywaa52uzwyb7x"},{"id":"mhj4li41ri7zdywaa52uzwyb7x","state":"close","txt":"\u81ea\u7136\u795e\u8bba","pid":"ksumra31z7mnh1bzqobv178vbz"},{"id":"z6434wk56i1lba1f72xz5vmakv","state":"none","txt":"\u72b9\u592a\u6559\u548c\u56de\u6559\u90fd\u76f8\u4fe1","pid":"tpxhuwkbwjrma5mi2zbsoype9p"},{"id":"8mhlspxohprkfbvyw6k286ei9h","state":"none","txt":"\u795e\u53ea\u6709\u4e00\u4f4d","pid":"tpxhuwkbwjrma5mi2zbsoype9p"},{"id":"tpxhuwkbwjrma5mi2zbsoype9p","state":"close","txt":"\u4e00\u795e\u8bba","pid":"ksumra31z7mnh1bzqobv178vbz"},{"id":"ed3x7foi2p4hm588lzrb2fzvwx","state":"none","txt":"\u597d\u795e\u548c\u574f\u795e","pid":"llr4fvetha7xl6xqppbzgkwnos"},{"id":"llr4fvetha7xl6xqppbzgkwnos","state":"close","txt":"\u4e8c\u795e\u8bba","pid":"ksumra31z7mnh1bzqobv178vbz"},{"id":"psozo8wzmispxrrn86za7qmxsf","state":"none","txt":"\u6709\u5f88\u591a\u795e","pid":"kyqwptl3jygibw23lbuhnrtbbv"},{"id":"kyqwptl3jygibw23lbuhnrtbbv","state":"close","txt":"\u591a\u795e\u8bba","pid":"ksumra31z7mnh1bzqobv178vbz"},{"id":"jdmhv6vqhultrsdulyd4kjd5o1","state":"none","txt":"\u51e1\u4e8b\u90fd\u662f\u795e","pid":"uyjkuo8fr15oemhqr2pjy73mbj"},{"id":"uyjkuo8fr15oemhqr2pjy73mbj","state":"close","txt":"\u6cdb\u7075\u8bba","pid":"ksumra31z7mnh1bzqobv178vbz"},{"id":"n2w916odart5s9b3r643mydd5f","state":"none","txt":"\u4e0d\u77e5\u9053\u4e16\u4e0a\u6709\u6ca1\u6709\u795e","pid":"hozqnpw73gve3s3kbkugd2bwro"},{"id":"hozqnpw73gve3s3kbkugd2bwro","state":"close","txt":"\u4e0d\u53ef\u77e5\u8bba","pid":"ksumra31z7mnh1bzqobv178vbz"},{"id":"j2t2frbnsst92djbw3sf4bbotq","state":"none","txt":"\u8ba4\u5b9a\u4e16\u4e0a\u6ca1\u6709\u795e","pid":"828dinzyiw655ru4kr4qhvvbwx"},{"id":"828dinzyiw655ru4kr4qhvvbwx","state":"close","txt":"\u65e0\u795e\u8bba","pid":"ksumra31z7mnh1bzqobv178vbz"},{"id":"mzqp8na7uzeb8uv2ppntqh7egq","state":"none","txt":"\u8bba\u548c\u4e3b\u4e49\u5927\u591a\u662f\u9519\u8bef\u7684\u89c2\u70b9","pid":"ksumra31z7mnh1bzqobv178vbz"},{"id":"ksumra31z7mnh1bzqobv178vbz","state":"close","txt":"\u54f2\u5b66\u4e4b\u95f4\u7684\u5dee\u5f02","pid":"f8hv17wi1nmlspa875ppvz8v28"},{"id":"59klab2pajk9egol9g55tbyx6q","state":"none","txt":"\u54f2\u5b66\u79cd\u7c7b\u7e41\u591a","pid":"9h8urbf1kxr9yix4uyibju2m1l"},{"id":"mljihaoua4rgsrw1nmqxhwudek","state":"none","txt":"\u4e3a\u4e8b\u7269\u627e\u5230\u7b54\u6848","pid":"1os476meybda1n1qfnlt6hefnu"},{"id":"1os476meybda1n1qfnlt6hefnu","state":"close","txt":"\u5185\u6db5","pid":"9h8urbf1kxr9yix4uyibju2m1l"},{"id":"bbb6w36gb2s1v7qdr29q5uufpa","state":"none","txt":"\u559c\u7231\u667a\u6167","pid":"6tnbofttg9ei8b1y72dabb8quj"},{"id":"6tnbofttg9ei8b1y72dabb8quj","state":"close","txt":"\u540d\u5b57\u7684\u542b\u4e49","pid":"9h8urbf1kxr9yix4uyibju2m1l"},{"id":"9h8urbf1kxr9yix4uyibju2m1l","state":"close","txt":"\u54f2\u5b66\u7684\u6982\u8ff0","pid":"f8hv17wi1nmlspa875ppvz8v28"},{"id":"f8hv17wi1nmlspa875ppvz8v28","state":"open","txt":"\u521b\u4e16\u7eaa\uff08\u5bfc\u8bfb02\uff09","pid":"canvas"}]}