{"wArr":[11,11,11,11,11],"twArr":[60,48,36,24,12],"maxlv":5,"topicArr":[{"id":"rj74fv6l7fq25wlue3s9r8yryr","state":"open","txt":"\u524d\u7aef\u77e5\u8bc6\u6846\u67b6","pid":"canvas"},{"id":"s4fqob6b7kblly1rkdvxh4disf","state":"open","txt":"JavaScript","pid":"rj74fv6l7fq25wlue3s9r8yryr"},{"id":"s1547ezmqsmeedxlvn8g1dika8","state":"open","txt":"\u53d8\u91cf\u548c\u7c7b\u578b","pid":"s4fqob6b7kblly1rkdvxh4disf"},{"id":"ariku24s7u2qovbudj3mgbkyds","state":"close","txt":"JavaScript\u89c4\u5b9a\u4e86\u51e0\u79cd\u53d8\u91cf\u7c7b\u578b\uff1f","pid":"s1547ezmqsmeedxlvn8g1dika8"},{"id":"1139zs9rxtkq2wlibbu1bembeg","state":"none","txt":"1. undefined","pid":"ariku24s7u2qovbudj3mgbkyds"},{"id":"b1tps66wsbyjxsx1vskpbu6mrp","state":"none","txt":"2. null","pid":"ariku24s7u2qovbudj3mgbkyds"},{"id":"6rt11eqxlwwdijlgjnoabokby1","state":"none","txt":"3. Bollean","pid":"ariku24s7u2qovbudj3mgbkyds"},{"id":"ds8vr99gfyubzbjx7hb362l32v","state":"none","txt":"4. String","pid":"ariku24s7u2qovbudj3mgbkyds"},{"id":"1q3nxlqk2z7mv8odkk19xwp3p5","state":"none","txt":"5. Number","pid":"ariku24s7u2qovbudj3mgbkyds"},{"id":"a2bogoxgjna6asi8oszklb6gei","state":"none","txt":"6. Symbol","pid":"ariku24s7u2qovbudj3mgbkyds"},{"id":"osrqxxbon9b4bpp7z41spsrhir","state":"none","txt":"7. Object","pid":"ariku24s7u2qovbudj3mgbkyds"},{"id":"vlba8n49xotwn4nr9zjjf9udzd","state":"none","txt":"JavaScript\u5bf9\u8c61\u7684\u5e95\u5c42\u6570\u636e\u7ed3\u6784\u662f\u4ec0\u4e48?","pid":"s1547ezmqsmeedxlvn8g1dika8"},{"id":"jqqgoedhqdq5u2ydgjfxx542n9","state":"none","txt":"Symbol\u7c7b\u578b\u5728\u5b9e\u9645\u5f00\u53d1\u4e2d\u7684\u5e94\u7528\uff1f\u624b\u52a8\u5b9e\u73b0\u4e00\u4e2a\u7b80\u5355\u7684Symbol","pid":"s1547ezmqsmeedxlvn8g1dika8"},{"id":"q7qy42pwtsrm27pngwy84inhyh","state":"none","txt":"JavaScript\u4e2d\u7684\u53d8\u91cf\u5728\u5185\u5b58\u4e2d\u7684\u5177\u4f53\u5b58\u50a8\u5f62\u5f0f\uff1f","pid":"s1547ezmqsmeedxlvn8g1dika8"},{"id":"uyir6fmknpjm6565u3f2kubbnb","state":"none","txt":"\u57fa\u672c\u7c7b\u578b\u5bf9\u5e94\u7684\u5185\u7f6e\u5bf9\u8c61\uff0c\u4ee5\u53ca\u4ed6\u4eec\u4e4b\u95f4\u7684\u88c5\u7bb1\u62c6\u7bb1\u64cd\u4f5c","pid":"s1547ezmqsmeedxlvn8g1dika8"},{"id":"orz377ptn333dqgyejb5x1u96u","state":"none","txt":"\u7406\u89e3\u503c\u7c7b\u578b\u548c\u5f15\u7528\u7c7b\u578b","pid":"s1547ezmqsmeedxlvn8g1dika8"},{"id":"rip33a3bzh7vp72sfabteyrhbv","state":"none","txt":"null\u548cundefined\u7684\u533a\u522b","pid":"s1547ezmqsmeedxlvn8g1dika8"},{"id":"498luy8iuhbbzb15bi35ojq3vt","state":"none","txt":"\u81f3\u5c11\u53ef\u4ee5\u8bf4\u51fa\u4e09\u79cd\u5224\u65adJavaScript\u6570\u636e\u7c7b\u578b\u7684\u65b9\u5f0f\uff0c\u4ee5\u53ca\u4ed6\u4eec\u7684\u4f18\u7f3a\u70b9\uff0c\u5982\u4f55\u51c6\u786e\u7684\u5224\u65ad\u6570\u7ec4\u7c7b\u578b","pid":"s1547ezmqsmeedxlvn8g1dika8"},{"id":"xw4xvtptinkt985jbnvb6kzq4y","state":"none","txt":"\u53ef\u80fd\u53d1\u751f\u9690\u5f0f\u7c7b\u578b\u8f6c\u6362\u7684\u573a\u666f\u4ee5\u53ca\u8f6c\u6362\u539f\u5219\uff0c\u5e94\u5982\u4f55\u907f\u514d\u6216\u5de7\u5999\u5e94\u7528","pid":"s1547ezmqsmeedxlvn8g1dika8"},{"id":"hawtpvzv23b2ilo2kks9syyql8","state":"none","txt":"\u51fa\u73b0\u5c0f\u6570\u7cbe\u5ea6\u4e22\u5931\u7684\u539f\u56e0\uff0cJavaScript\u53ef\u4ee5\u5b58\u50a8\u7684\u6700\u5927\u6570\u5b57\u3001\u6700\u5927\u5b89\u5168\u6570\u5b57\uff0cJavaScript\u5904\u7406\u5927\u6570\u5b57\u7684\u65b9\u6cd5\u3001\u907f\u514d\u7cbe\u5ea6\u4e22\u5931\u7684\u65b9\u6cd5","pid":"s1547ezmqsmeedxlvn8g1dika8"},{"id":"9kg9l2bxzjhw4x4u9jb26yga6u","state":"close","txt":"\u539f\u578b\u548c\u539f\u578b\u94fe","pid":"s4fqob6b7kblly1rkdvxh4disf"},{"id":"qx7hbnm1d8qbybs6w216babq3o","state":"none","txt":"\u7406\u89e3\u539f\u578b\u8bbe\u8ba1\u6a21\u5f0f\u4ee5\u53caJavaScript\u4e2d\u7684\u539f\u578b\u89c4\u5219","pid":"9kg9l2bxzjhw4x4u9jb26yga6u"},{"id":"b15ad5xv1wdpvgb86do3dkekt5","state":"none","txt":"instanceof\u7684\u5e95\u5c42\u5b9e\u73b0\u539f\u7406\uff0c\u624b\u52a8\u5b9e\u73b0\u4e00\u4e2ainstanceof","pid":"9kg9l2bxzjhw4x4u9jb26yga6u"},{"id":"dxb644b41w9yssy6im9lkzvhzb","state":"none","txt":"\u5b9e\u73b0\u7ee7\u627f\u7684\u51e0\u79cd\u65b9\u5f0f\u4ee5\u53ca\u4ed6\u4eec\u7684\u4f18\u7f3a\u70b9","pid":"9kg9l2bxzjhw4x4u9jb26yga6u"},{"id":"7vhq64ywkwwypgiuyebaba61ab","state":"none","txt":"\u81f3\u5c11\u8bf4\u51fa\u4e00\u79cd\u5f00\u6e90\u9879\u76ee(\u5982Node)\u4e2d\u5e94\u7528\u539f\u578b\u7ee7\u627f\u7684\u6848\u4f8b","pid":"9kg9l2bxzjhw4x4u9jb26yga6u"},{"id":"kaqkabtwr96u13lknldkbafu2l","state":"none","txt":"\u53ef\u4ee5\u63cf\u8ff0new\u4e00\u4e2a\u5bf9\u8c61\u7684\u8be6\u7ec6\u8fc7\u7a0b\uff0c\u624b\u52a8\u5b9e\u73b0\u4e00\u4e2anew\u64cd\u4f5c\u7b26","pid":"9kg9l2bxzjhw4x4u9jb26yga6u"},{"id":"bbsti8x4bu1xlzkqdkrvhqzt9b","state":"none","txt":"\u7406\u89e3es6 class\u6784\u9020\u4ee5\u53ca\u7ee7\u627f\u7684\u5e95\u5c42\u5b9e\u73b0\u539f\u7406","pid":"9kg9l2bxzjhw4x4u9jb26yga6u"},{"id":"eiq62f6yv9b65p7unstyx3ot1h","state":"close","txt":"\u4f5c\u7528\u57df\u548c\u95ed\u5305","pid":"s4fqob6b7kblly1rkdvxh4disf"},{"id":"1fown56m6jss9yvmb5xy1vd91m","state":"none","txt":"\u7406\u89e3\u8bcd\u6cd5\u4f5c\u7528\u57df\u548c\u52a8\u6001\u4f5c\u7528\u57df","pid":"eiq62f6yv9b65p7unstyx3ot1h"},{"id":"rb3bq4weq3mrrr57vlzky1yko2","state":"none","txt":"\u7406\u89e3JavaScript\u7684\u4f5c\u7528\u57df\u548c\u4f5c\u7528\u57df\u94fe","pid":"eiq62f6yv9b65p7unstyx3ot1h"},{"id":"yj7w5tfiss4guoxtjo1h16vpv2","state":"none","txt":"\u7406\u89e3JavaScript\u7684\u6267\u884c\u4e0a\u4e0b\u6587\u6808\uff0c\u53ef\u4ee5\u5e94\u7528\u5806\u6808\u4fe1\u606f\u5feb\u901f\u5b9a\u4f4d\u95ee\u9898","pid":"eiq62f6yv9b65p7unstyx3ot1h"},{"id":"2z4hvgrxtjigd4vr5fl9zde8gq","state":"none","txt":"this\u7684\u539f\u7406\u4ee5\u53ca\u51e0\u79cd\u4e0d\u540c\u4f7f\u7528\u573a\u666f\u7684\u53d6\u503c","pid":"eiq62f6yv9b65p7unstyx3ot1h"},{"id":"fin7786lkb9atzqvf7b8is41h2","state":"none","txt":"\u95ed\u5305\u7684\u5b9e\u73b0\u539f\u7406\u548c\u4f5c\u7528\uff0c\u53ef\u4ee5\u5217\u4e3e\u51e0\u4e2a\u5f00\u53d1\u4e2d\u95ed\u5305\u7684\u5b9e\u9645\u5e94\u7528","pid":"eiq62f6yv9b65p7unstyx3ot1h"},{"id":"5n5b3rvgdop3lvlyi4jgoggqdo","state":"none","txt":"\u7406\u89e3\u5806\u6808\u6ea2\u51fa\u548c\u5185\u5b58\u6cc4\u6f0f\u7684\u539f\u7406\uff0c\u5982\u4f55\u9632\u6b62","pid":"eiq62f6yv9b65p7unstyx3ot1h"},{"id":"f159x12mxohhbr69ja1pzizohs","state":"none","txt":"\u5982\u4f55\u5904\u7406\u5faa\u73af\u7684\u5f02\u6b65\u64cd\u4f5c","pid":"eiq62f6yv9b65p7unstyx3ot1h"},{"id":"bskb4qviquzl92kev66vxo8wmj","state":"none","txt":"\u7406\u89e3\u6a21\u5757\u5316\u89e3\u51b3\u7684\u5b9e\u9645\u95ee\u9898\uff0c\u53ef\u5217\u4e3e\u51e0\u4e2a\u6a21\u5757\u5316\u65b9\u6848\u5e76\u7406\u89e3\u5176\u4e2d\u539f\u7406","pid":"eiq62f6yv9b65p7unstyx3ot1h"},{"id":"goapsp3t2libjsqebyivephi9m","state":"close","txt":"\u6267\u884c\u673a\u5236","pid":"s4fqob6b7kblly1rkdvxh4disf"},{"id":"z7iaiznp53sjvsrovsaqapqthi","state":"none","txt":"\u4e3a\u4f55try\u91cc\u9762\u653ereturn\uff0cfinally\u8fd8\u4f1a\u6267\u884c\uff0c\u7406\u89e3\u5176\u5185\u90e8\u673a\u5236","pid":"goapsp3t2libjsqebyivephi9m"},{"id":"8bas6t3jm757pjzi1hwbb9vuyu","state":"none","txt":"JavaScript\u5982\u4f55\u5b9e\u73b0\u5f02\u6b65\u7f16\u7a0b\uff0c\u53ef\u4ee5\u8be6\u7ec6\u63cf\u8ff0EventLoop\u673a\u5236","pid":"goapsp3t2libjsqebyivephi9m"},{"id":"yonhm4bjzsuq2qtgoi41qoosp3","state":"none","txt":"\u5b8f\u4efb\u52a1\u548c\u5fae\u4efb\u52a1\u5206\u522b\u6709\u54ea\u4e9b","pid":"goapsp3t2libjsqebyivephi9m"},{"id":"hhyv2hn3uog6bpdfe3zpobbqog","state":"none","txt":"\u53ef\u4ee5\u5feb\u901f\u5206\u6790\u4e00\u4e2a\u590d\u6742\u7684\u5f02\u6b65\u5d4c\u5957\u903b\u8f91\uff0c\u5e76\u638c\u63e1\u5206\u6790\u65b9\u6cd5","pid":"goapsp3t2libjsqebyivephi9m"},{"id":"62ilrlt4tk4bndqmwtouhlfhmf","state":"none","txt":"\u4f7f\u7528Promise\u5b9e\u73b0\u4e32\u884c","pid":"goapsp3t2libjsqebyivephi9m"},{"id":"kexui6qx39exazi8xir3bgxjra","state":"none","txt":"Node\u4e0e\u6d4f\u89c8\u5668EventLoop\u7684\u5dee\u5f02","pid":"goapsp3t2libjsqebyivephi9m"},{"id":"n6tvesw3viy4sx8oumh5simgd7","state":"none","txt":"\u5982\u4f55\u5728\u4fdd\u8bc1\u9875\u9762\u8fd0\u884c\u6d41\u7545\u7684\u60c5\u51b5\u4e0b\u5904\u7406\u6d77\u91cf\u6570\u636e","pid":"goapsp3t2libjsqebyivephi9m"},{"id":"gxhkvtel9zz14ro3vzqb5bdzj4","state":"close","txt":"\u8bed\u6cd5\u548cAPI","pid":"s4fqob6b7kblly1rkdvxh4disf"},{"id":"qkz927opeuzswsisod35dmlufq","state":"none","txt":"\u7406\u89e3ECMAScript\u548cJavaScript\u7684\u5173\u7cfb","pid":"gxhkvtel9zz14ro3vzqb5bdzj4"},{"id":"1x4tbddp9g5br2qb5guhhznbst","state":"none","txt":"\u719f\u7ec3\u8fd0\u7528es5\u3001es6\u63d0\u4f9b\u7684\u8bed\u6cd5\u89c4\u8303","pid":"gxhkvtel9zz14ro3vzqb5bdzj4"},{"id":"lyzz5gbrqjwxg8vmk8fu1f3y3w","state":"none","txt":"\u719f\u7ec3\u638c\u63e1JavaScript\u63d0\u4f9b\u7684\u5168\u5c40\u5bf9\u8c61\uff08\u4f8b\u5982Date\u3001Math\uff09\u3001\u5168\u5c40\u51fd\u6570\uff08\u4f8b\u5982decodeURI\u3001isNaN\uff09\u3001\u5168\u5c40\u5c5e\u6027\uff08\u4f8b\u5982Infinity\u3001undefined\uff09","pid":"gxhkvtel9zz14ro3vzqb5bdzj4"},{"id":"7izbab9tznssbplrdlaxwdvipj","state":"none","txt":"\u719f\u7ec3\u5e94\u7528map\u3001reduce\u3001filter \u7b49\u9ad8\u9636\u51fd\u6570\u89e3\u51b3\u95ee\u9898","pid":"gxhkvtel9zz14ro3vzqb5bdzj4"},{"id":"4a16dtm7zgt8b5rwy66gmhdkud","state":"none","txt":"setInterval\u9700\u8981\u6ce8\u610f\u7684\u70b9\uff0c\u4f7f\u7528settimeout\u5b9e\u73b0setInterval","pid":"gxhkvtel9zz14ro3vzqb5bdzj4"},{"id":"im28bqo5fogjyt1ia9nd2jswo2","state":"none","txt":"JavaScript\u63d0\u4f9b\u7684\u6b63\u5219\u8868\u8fbe\u5f0fAPI\u3001\u53ef\u4ee5\u4f7f\u7528\u6b63\u5219\u8868\u8fbe\u5f0f\uff08\u90ae\u7bb1\u6821\u9a8c\u3001URL\u89e3\u6790\u3001\u53bb\u91cd\u7b49\uff09\u89e3\u51b3\u5e38\u89c1\u95ee\u9898","pid":"gxhkvtel9zz14ro3vzqb5bdzj4"},{"id":"5f7fx5e84r6ubmmpqoxipuruan","state":"none","txt":"JavaScript\u5f02\u5e38\u5904\u7406\u7684\u65b9\u5f0f\uff0c\u7edf\u4e00\u7684\u5f02\u5e38\u5904\u7406\u65b9\u6848","pid":"gxhkvtel9zz14ro3vzqb5bdzj4"},{"id":"hjp1hb5p4uen4r54zj6rmqo3md","state":"close","txt":"HTML\u548cCSS","pid":"rj74fv6l7fq25wlue3s9r8yryr"},{"id":"4f215ep3vb3mdmhuwlsbykero5","state":"open","txt":"Html","pid":"hjp1hb5p4uen4r54zj6rmqo3md"},{"id":"v3uaonsh776i1u1ymr2ovegyz5","state":"none","txt":"\u4ece\u89c4\u8303\u7684\u89d2\u5ea6\u7406\u89e3HTML\uff0c\u4ece\u5206\u7c7b\u548c\u8bed\u4e49\u7684\u89d2\u5ea6\u4f7f\u7528\u6807\u7b7e","pid":"4f215ep3vb3mdmhuwlsbykero5"},{"id":"detg1qsnxljq8mtwnirubsgf1p","state":"none","txt":"\u5e38\u7528\u9875\u9762\u6807\u7b7e\u7684\u9ed8\u8ba4\u6837\u5f0f\u3001\u81ea\u5e26\u5c5e\u6027\u3001\u4e0d\u540c\u6d4f\u89c8\u5668\u7684\u5dee\u5f02\u3001\u5904\u7406\u6d4f\u89c8\u5668\u517c\u5bb9\u95ee\u9898\u7684\u65b9\u5f0f","pid":"4f215ep3vb3mdmhuwlsbykero5"},{"id":"pwf4eibx5v7n8mytoq5tl3dq27","state":"none","txt":"\u5143\u4fe1\u606f\u7c7b\u6807\u7b7e(head\u3001title\u3001meta)\u7684\u4f7f\u7528\u76ee\u7684\u548c\u914d\u7f6e\u65b9\u6cd5","pid":"4f215ep3vb3mdmhuwlsbykero5"},{"id":"6evs4651384qa3pharqtpj2b3w","state":"none","txt":"HTML5\u79bb\u7ebf\u7f13\u5b58\u539f\u7406","pid":"4f215ep3vb3mdmhuwlsbykero5"},{"id":"i5is1jynivje6zqh5zgrdo92mn","state":"none","txt":"\u53ef\u4ee5\u4f7f\u7528Canvas API\u3001SVG\u7b49\u7ed8\u5236\u9ad8\u6027\u80fd\u7684\u52a8\u753b","pid":"4f215ep3vb3mdmhuwlsbykero5"},{"id":"pzt6n51ps4pbzuixu465ljbpng","state":"open","txt":"CSS","pid":"hjp1hb5p4uen4r54zj6rmqo3md"},{"id":"55bft4m56qlbaf4aqpwjygl32b","state":"none","txt":"CSS\u76d2\u6a21\u578b\uff0c\u5728\u4e0d\u540c\u6d4f\u89c8\u5668\u7684\u5dee\u5f02","pid":"pzt6n51ps4pbzuixu465ljbpng"},{"id":"q12edk5467463brib2t1b9aish","state":"none","txt":"CSS\u6240\u6709\u9009\u62e9\u5668\u53ca\u5176\u4f18\u5148\u7ea7\u3001\u4f7f\u7528\u573a\u666f\uff0c\u54ea\u4e9b\u53ef\u4ee5\u7ee7\u627f\uff0c\u5982\u4f55\u8fd0\u7528at\u89c4\u5219","pid":"pzt6n51ps4pbzuixu465ljbpng"},{"id":"2oft4v4zswd2jqjo3wbrbaq21m","state":"none","txt":"CSS\u4f2a\u7c7b\u548c\u4f2a\u5143\u7d20\u6709\u54ea\u4e9b\uff0c\u5b83\u4eec\u7684\u533a\u522b\u548c\u5b9e\u9645\u5e94\u7528","pid":"pzt6n51ps4pbzuixu465ljbpng"},{"id":"bs9mo8ywnwg53dpny7yhobyn7d","state":"none","txt":"HTML\u6587\u6863\u6d41\u7684\u6392\u7248\u89c4\u5219\uff0cCSS\u51e0\u79cd\u5b9a\u4f4d\u7684\u89c4\u5219\u3001\u5b9a\u4f4d\u53c2\u7167\u7269\u3001\u5bf9\u6587\u6863\u6d41\u7684\u5f71\u54cd\uff0c\u5982\u4f55\u9009\u62e9\u6700\u597d\u7684\u5b9a\u4f4d\u65b9\u5f0f\uff0c\u96ea\u78a7\u56fe\u5b9e\u73b0\u539f\u7406","pid":"pzt6n51ps4pbzuixu465ljbpng"},{"id":"8e9m2undbsyo5b6s4ghf366131","state":"none","txt":"\u6c34\u5e73\u5782\u76f4\u5c45\u4e2d\u7684\u65b9\u6848\u3001\u53ef\u4ee5\u5b9e\u73b06\u79cd\u4ee5\u4e0a\u5e76\u5bf9\u6bd4\u5b83\u4eec\u7684\u4f18\u7f3a\u70b9","pid":"pzt6n51ps4pbzuixu465ljbpng"},{"id":"uwrr3lvus5bj2r3wjo3pw9232l","state":"none","txt":"BFC\u5b9e\u73b0\u539f\u7406\uff0c\u53ef\u4ee5\u89e3\u51b3\u7684\u95ee\u9898\uff0c\u5982\u4f55\u521b\u5efaBFC","pid":"pzt6n51ps4pbzuixu465ljbpng"},{"id":"t8ljhn3ns79raphvfbion5alot","state":"none","txt":"\u53ef\u4f7f\u7528CSS\u51fd\u6570\u590d\u7528\u4ee3\u7801\uff0c\u5b9e\u73b0\u7279\u6b8a\u6548\u679c","pid":"pzt6n51ps4pbzuixu465ljbpng"},{"id":"6boid7bzapla1haz7tyr9s9ett","state":"none","txt":"PostCSS\u3001Sass\u3001Less\u7684\u5f02\u540c\uff0c\u4ee5\u53ca\u4f7f\u7528\u914d\u7f6e\uff0c\u81f3\u5c11\u638c\u63e1\u4e00\u79cd","pid":"pzt6n51ps4pbzuixu465ljbpng"},{"id":"servswo9xo87ubskit3wfzoh8z","state":"none","txt":"CSS\u6a21\u5757\u5316\u65b9\u6848\u3001\u5982\u4f55\u914d\u7f6e\u6309\u9700\u52a0\u8f7d\u3001\u5982\u4f55\u9632\u6b62CSS\u963b\u585e\u6e32\u67d3\n","pid":"pzt6n51ps4pbzuixu465ljbpng"},{"id":"ok94oe97xf5u8dxx1knhlfk4dl","state":"none","txt":"\u719f\u7ec3\u4f7f\u7528CSS\u5b9e\u73b0\u5e38\u89c1\u52a8\u753b\uff0c\u5982\u6e10\u53d8\u3001\u79fb\u52a8\u3001\u65cb\u8f6c\u3001\u7f29\u653e\u7b49\u7b49","pid":"pzt6n51ps4pbzuixu465ljbpng"},{"id":"vok38b824jt997xt4l3ub2b1o5","state":"none","txt":"CSS\u6d4f\u89c8\u5668\u517c\u5bb9\u6027\u5199\u6cd5\uff0c\u4e86\u89e3\u4e0d\u540cAPI\u5728\u4e0d\u540c\u6d4f\u89c8\u5668\u4e0b\u7684\u517c\u5bb9\u6027\u60c5\u51b5","pid":"pzt6n51ps4pbzuixu465ljbpng"},{"id":"g83uf87thrsmwtqjpa939v7xrv","state":"none","txt":"\u638c\u63e1\u4e00\u5957\u5b8c\u6574\u7684\u54cd\u5e94\u5f0f\u5e03\u5c40\u65b9\u6848","pid":"pzt6n51ps4pbzuixu465ljbpng"},{"id":"gjfrvtkw71pto69wbjwhm74gag","state":"open","txt":"\u624b\u5199","pid":"hjp1hb5p4uen4r54zj6rmqo3md"},{"id":"gkuh4ygvd3rsmxtufupmiqyehu","state":"none","txt":"\u624b\u5199\u56fe\u7247\u7011\u5e03\u6d41\u6548\u679c","pid":"gjfrvtkw71pto69wbjwhm74gag"},{"id":"jhalfxhhftoo73ponmiyzptp2v","state":"none","txt":"\u4f7f\u7528CSS\u7ed8\u5236\u51e0\u4f55\u56fe\u5f62\uff08\u5706\u5f62\u3001\u4e09\u89d2\u5f62\u3001\u6247\u5f62\u3001\u83f1\u5f62\u7b49\uff09","pid":"gjfrvtkw71pto69wbjwhm74gag"},{"id":"647u1akk1og84bolz8b5z9w3jk","state":"none","txt":"\u4f7f\u7528\u7eafCSS\u5b9e\u73b0\u66f2\u7ebf\u8fd0\u52a8\uff08\u8d1d\u585e\u5c14\u66f2\u7ebf\uff09","pid":"gjfrvtkw71pto69wbjwhm74gag"},{"id":"at6syb8a11frso2zoom4xgs5ws","state":"none","txt":"\u5b9e\u73b0\u5e38\u7528\u5e03\u5c40\uff08\u4e09\u680f\u3001\u5723\u676f\u3001\u53cc\u98de\u7ffc\u3001\u5438\u9876\uff09\uff0c\u53ef\u662f\u8bf4\u51fa\u591a\u79cd\u65b9\u5f0f\u5e76\u7406\u89e3\u5176\u4f18\u7f3a\u70b9","pid":"gjfrvtkw71pto69wbjwhm74gag"}]}