{"wArr":[12.125,8,17.1875],"twArr":[40.3125,27.1875,18.1875],"maxlv":3,"topicArr":[{"id":"3566tx1vautlwhoz6w8sxjqi25","state":"open","txt":"Material Design\u8272\u677f","pid":"canvas"},{"id":"2ul4raf3lanebiwpd46dn568zb","state":"close","txt":"\u84dd\u7070 #607d8b","pid":"3566tx1vautlwhoz6w8sxjqi25","image":"http:\/\/mapi.weavent.com\/image\/view\/c948f66dd91a00f925063b21df9edd30_256.png"},{"id":"nar59vrv77bxhu6t86d5uabu75","state":"none","txt":"Blue Grey, RGB(96, 125, 139)","pid":"2ul4raf3lanebiwpd46dn568zb","image":"http:\/\/mapi.weavent.com\/image\/view\/8d7aec6caee4fca4785f2111ca447fba_610.png"},{"id":"xgb4i6zrshofvs73p1wpwi8q4f","state":"close","txt":"\u7070\u8272 #9e9e9e","pid":"3566tx1vautlwhoz6w8sxjqi25","image":"http:\/\/mapi.weavent.com\/image\/view\/7483453ba36808af106aa18aa4decd49_256.png"},{"id":"356x3yp5ftvu2jjdxu7zxrmhpd","state":"none","txt":"Grey, RGB(158, 158, 158)","pid":"xgb4i6zrshofvs73p1wpwi8q4f","image":"http:\/\/mapi.weavent.com\/image\/view\/d4eadcf94e7d9f8aa402be85a494ddfc_610.png"},{"id":"mjxqbwgfoohnnfwqp742k18os7","state":"close","txt":"\u68d5\u8272 #795548","pid":"3566tx1vautlwhoz6w8sxjqi25","image":"http:\/\/mapi.weavent.com\/image\/view\/032c7f9d70e1ab57319f373412fee423_256.png"},{"id":"rhbxaut3kvfvusuqpj3bdobuto","state":"none","txt":"Brown, RGB(121, 85, 72)","pid":"mjxqbwgfoohnnfwqp742k18os7","image":"http:\/\/mapi.weavent.com\/image\/view\/f3fb77ce54310bedca0eb114677b8761_610.png"},{"id":"53rz89e4gv37b95xu1mebowqwk","state":"close","txt":"\u6df1\u6854 #ff5722","pid":"3566tx1vautlwhoz6w8sxjqi25","image":"http:\/\/mapi.weavent.com\/image\/view\/df6716867af89fd26c6df526f2b7e5cf_256.png"},{"id":"zblfykbk7ea9ijkz1z33p2wwi6","state":"none","txt":"Deep Orange, RGB(255, 87 ,34)","pid":"53rz89e4gv37b95xu1mebowqwk","image":"http:\/\/mapi.weavent.com\/image\/view\/6ba4803d371de12de868b7be14573064_610.png"},{"id":"ltsy2gtl9sv3ty57m3k741wejt","state":"close","txt":"\u6a58\u9ec4 #ff9800","pid":"3566tx1vautlwhoz6w8sxjqi25","image":"http:\/\/mapi.weavent.com\/image\/view\/d3fc20c54c2de71a87417a00b6adbc57_256.png"},{"id":"mh5j8g7q1pr1lsi62vxt612mpl","state":"none","txt":"Orange, RGB(255, 152, 0)","pid":"ltsy2gtl9sv3ty57m3k741wejt","image":"http:\/\/mapi.weavent.com\/image\/view\/df0b7e854788e434db63296a0728cbc9_610.png"},{"id":"de4qo3fapwlpgrdj2bdp9xzh8d","state":"close","txt":"\u7425\u73c0 #ffc107","pid":"3566tx1vautlwhoz6w8sxjqi25","image":"http:\/\/mapi.weavent.com\/image\/view\/7671595ac67978314e0a3d24187246c2_256.png"},{"id":"vltzb9dfrhb3fmef7415ybkshd","state":"none","txt":"Amber, RGB(255, 193, 7)","pid":"de4qo3fapwlpgrdj2bdp9xzh8d","image":"http:\/\/mapi.weavent.com\/image\/view\/ba5e605031fde08390200fe3f9f2798c_610.png"},{"id":"bbbri3gf2m3v2ynr7zrggu1dlt","state":"close","txt":"\u9ec4\u8272 #ffeb3b","pid":"3566tx1vautlwhoz6w8sxjqi25","image":"http:\/\/mapi.weavent.com\/image\/view\/7ba16d0871b00bd7b70fd9ef01b81743_256.png"},{"id":"a1zej6eabf5l9mpfx6ea3a1pd2","state":"none","txt":"Yellow, RGB(255, 235, 59)","pid":"bbbri3gf2m3v2ynr7zrggu1dlt","image":"http:\/\/mapi.weavent.com\/image\/view\/f96402c88affa0f9e3d8b11aa118cf5d_610.png"},{"id":"safiwgebslq8bfqebbboklyf3d","state":"close","txt":"\u9178\u6a59 #cddc39","pid":"3566tx1vautlwhoz6w8sxjqi25","image":"http:\/\/mapi.weavent.com\/image\/view\/58ca5c5ef2e1f05cd94aa3d2340740c2_256.png"},{"id":"kgm2svqiq55rzp3msomijok1t3","state":"none","txt":"Lime, RGB(205, 220 ,57)","pid":"safiwgebslq8bfqebbboklyf3d","image":"http:\/\/mapi.weavent.com\/image\/view\/568e8677a58345e0bfdb1bf8fd565cda_610.png"},{"id":"nmmjddhlmn8ovpbnxx9zp69mgz","state":"close","txt":"\u6d45\u7eff #8bc34a","pid":"3566tx1vautlwhoz6w8sxjqi25","image":"http:\/\/mapi.weavent.com\/image\/view\/1481d9b5fe0f0c3cee3be0df21d6aa1b_256.png"},{"id":"z5uy5dymg24xtwg4n3gl87124y","state":"none","txt":"Light Green, RGB(139, 195, 74)","pid":"nmmjddhlmn8ovpbnxx9zp69mgz","image":"http:\/\/mapi.weavent.com\/image\/view\/afa6bf01bb4571e5b05b310508a7bf12_610.png"},{"id":"38bxqwkbrzhssq69fp3nrbq4oi","state":"close","txt":"\u7eff\u8272 #259b24","pid":"3566tx1vautlwhoz6w8sxjqi25","image":"http:\/\/mapi.weavent.com\/image\/view\/46a0a93b7b044570d9002c0002c33c89_256.png"},{"id":"sb62iulq4lisgy2sj9p9s3azb9","state":"none","txt":"Green, RGB(37, 155, 36)","pid":"38bxqwkbrzhssq69fp3nrbq4oi","image":"http:\/\/mapi.weavent.com\/image\/view\/fd9e303516340ec2f0727b56f38f267e_610.png"},{"id":"4b5uyzly4l7pvebpvkq1omw2q6","state":"close","txt":"\u84dd\u7eff #009688","pid":"3566tx1vautlwhoz6w8sxjqi25","image":"http:\/\/mapi.weavent.com\/image\/view\/ad9845793170a5d6bdae1ba7f2659c2b_256.png"},{"id":"5fbapd1n9xym856ng5tpi8sfb7","state":"none","txt":"Teal, RGB(0, 150, 136)","pid":"4b5uyzly4l7pvebpvkq1omw2q6","image":"http:\/\/mapi.weavent.com\/image\/view\/efa79855b0655110ff3fbe40ef5fcef1_610.png"},{"id":"en8gm8djlaiwoenr1i75er7ztv","state":"close","txt":"\u9752\u8272 #00bcd4","pid":"3566tx1vautlwhoz6w8sxjqi25","image":"http:\/\/mapi.weavent.com\/image\/view\/6a241be8c42da55ce1a5854636d85513_256.png"},{"id":"zb6a5vheyhir6jove17hfjsfxn","state":"none","txt":"Cyan, RGB(0, 188 ,212)","pid":"en8gm8djlaiwoenr1i75er7ztv","image":"http:\/\/mapi.weavent.com\/image\/view\/91d4c7c2a76c0d94b16667eb7217869e_610.png"},{"id":"8x8l3138k48b63jvhsp2b6fxbd","state":"close","txt":"\u6d45\u84dd #03a9f4","pid":"3566tx1vautlwhoz6w8sxjqi25","image":"http:\/\/mapi.weavent.com\/image\/view\/d93586ce232cdfd1ec2e2b6fb6553dd4_256.png"},{"id":"laygilq8ivrt6ev653wrybtjxg","state":"none","txt":"Light Blue, RGB(3, 169, 244)","pid":"8x8l3138k48b63jvhsp2b6fxbd","image":"http:\/\/mapi.weavent.com\/image\/view\/7e7e3b2e1b685b731f7188c59e53bac9_610.png"},{"id":"9g5p8z4o7soxvqgy8pvv7zvw7z","state":"close","txt":"\u84dd\u8272 #5677fc","pid":"3566tx1vautlwhoz6w8sxjqi25","image":"http:\/\/mapi.weavent.com\/image\/view\/56ef41b17edb8516b359655c82882b6c_256.png"},{"id":"s2zvbbmiaif25jxdw9t6gxoun4","state":"none","txt":"Blue, RGB(86, 119, 252)","pid":"9g5p8z4o7soxvqgy8pvv7zvw7z","image":"http:\/\/mapi.weavent.com\/image\/view\/1776166dc5ec83c38be0d1bd18a4fec2_610.png"},{"id":"nfsmisegel4bt8kala71psa6ip","state":"close","txt":"\u975b\u84dd #3f51b5","pid":"3566tx1vautlwhoz6w8sxjqi25","image":"http:\/\/mapi.weavent.com\/image\/view\/6811770738060998226aefa96e2bbfd3_256.png"},{"id":"1jtw9h4xa1vropqmyfbqrwvftg","state":"none","txt":"Indigo, RGB(63, 81, 181)","pid":"nfsmisegel4bt8kala71psa6ip","image":"http:\/\/mapi.weavent.com\/image\/view\/e0143f3b2f8f879fcd4116a440830762_610.png"},{"id":"i8xlbh1qnj5575xdyb7jdoe2nf","state":"close","txt":"\u6df1\u7d2b #673ab7","pid":"3566tx1vautlwhoz6w8sxjqi25","image":"http:\/\/mapi.weavent.com\/image\/view\/6f59f28894eea9e03a21624827b91277_256.png"},{"id":"kburkr2p4nuzn9484am68m6pzg","state":"none","txt":"Deep Purple, RGB(103, 58, 183)","pid":"i8xlbh1qnj5575xdyb7jdoe2nf","image":"http:\/\/mapi.weavent.com\/image\/view\/ea9cf392b973956e0a2ee575075ded23_610.png"},{"id":"u1juzkkawpe6fp2m5ovitq11zz","state":"close","txt":"\u7d2b\u8272 #9c27b0","pid":"3566tx1vautlwhoz6w8sxjqi25","image":"http:\/\/mapi.weavent.com\/image\/view\/1a36ec1a2f22d64063a80b8f7b1e1f9e_256.png"},{"id":"2fwp479l2edy1hw69oka646lmp","state":"none","txt":"Purple, RGB(156, 39, 176)","pid":"u1juzkkawpe6fp2m5ovitq11zz","image":"http:\/\/mapi.weavent.com\/image\/view\/c2c98d5819731d5f3f31058cf6651161_750.png"},{"id":"zej928ee14nw5rool4fpmuhxhp","state":"close","txt":"\u7c89\u8272 #e91e63","pid":"3566tx1vautlwhoz6w8sxjqi25","image":"http:\/\/mapi.weavent.com\/image\/view\/4062c150a2f68516c35db3630b109878_256.png"},{"id":"f7zm5si8936276bohtp6lnywst","state":"none","txt":"Pink, RGB(233, 30, 99)","pid":"zej928ee14nw5rool4fpmuhxhp","image":"http:\/\/mapi.weavent.com\/image\/view\/aca4381d7d8f28c4a225099e2dad92e9_750.png"},{"id":"1yi64o83i9be9zjznyow8yefvp","state":"close","txt":"\u7ea2\u8272 #e51c23","pid":"3566tx1vautlwhoz6w8sxjqi25","image":"http:\/\/mapi.weavent.com\/image\/view\/de8a8d5812c0a5eb0ac71bae4e535b0e_256.png"},{"id":"34t56ooebt8hxm3fnk5tx9k32t","state":"none","txt":"Red, RGB(229, 28, 35)","pid":"1yi64o83i9be9zjznyow8yefvp","image":"http:\/\/mapi.weavent.com\/image\/view\/e756b479f5a0e2de0d918b1326fbbf99_750.png"}]}